{"hiddenService":"3z3aemj4a2xmxg3t.onion","webDetected":true,"sshDetected":false,"ricochetDetected":false,"ircDetected":false,"ftpDetected":false,"smtpDetected":false,"bitcoinDetected":false,"mongodbDetected":false,"vncDetected":false,"xmppDetected":false,"serverPoweredBy":"","serverVersion":"","foundApacheModStatus":false,"relatedOnionServices":null,"relatedOnionDomains":null,"linkedSites":["kdq2y44aaas2aiu4.onion","www.w3.org","creativecommons.org","www.rawr-designs.com","ajax.googleapis.com"],"internalPages":[""],"ipAddresses":null,"openDirectories":null,"exifImages":null,"interestingFiles":null,"pageReferencedDirectories":["/template/red","/template/global","/template/global/topup","/template/global","Login","/template/red/images/icons","Login"],"pgpKeys":null,"hashes":["6874e7d1c11c9c0ec90ede728606f709a9565670"],"snapshot":"\u003c!DOCTYPE html PUBLIC \"-//W3C//DTD XHTML 1.0 Transitional//EN\" \"http://www.w3.org/TR/xhtml1/DTD/xhtml1-transitional.dtd\"\u003e\r\n\u003chtml xmlns=\"http://www.w3.org/1999/xhtml\"\u003e\r\n\u003c!--\r\n  Live - 3.0.1\r\n\r\n (c) 2009-2010, RAWR-Designs, Some Rights Reserved -\r\n        Christopher \"That Stevens Guy\" Stevens\r\n        Richard \"Giant Eagle\" Tuininga\r\n\r\n (cc) http://creativecommons.org/licenses/by-nc-sa/3.0\r\n\r\n  Any queries? -\r\n        Email: contact[at]rawr-designs.com\r\n        Forum: http://www.rawr-designs.com/forum/\r\n         Homepage: http://www.rawr-designs.com\r\n--\u003e\r\n\r\n\u003chead\u003e\r\n\u003clink rel=\"shortcut icon\" href=\"favicon.ico\"\u003e\r\n\u003c/head\u003e\r\n\r\n\u003chead\u003e\r\n        \u003ctitle\u003eUPA - Gallery/\u003c/title\u003e\r\n        \u003cmeta http-equiv=\"Content-Type\" content=\"text/html; charset=UTF-8\"/\u003e\r\n        \u003cmeta name=\"robots\" content=\"noindex, nofollow\"/\u003e\r\n        \u003clink rel=\"shortcut icon\" href=\"/favicon.ico\"/\u003e\r\n        \u003clink rel=\"stylesheet\" type=\"text/css\" href=\"/template/red/live.style.red.css\"/\u003e\r\n        \u003cscript type=\"text/javascript\" src=\"http://ajax.googleapis.com/ajax/libs/jquery/1/jquery.min.js\"\u003e\u003c/script\u003e\r\n        \u003cscript type=\"text/javascript\"\u003e\r\n                if (typeof jQuery == 'undefined') document.write('\u003cscript type=\"text/javascript\" src=\"/template/global/jquery.packed.js\"\u003e\u003c/'+'script\u003e');\r\n                HFS={\r\n                 folder:'/',\r\n                 archive_enabled:true,\r\n                 delete_enabled:false,\r\n                 upload_enabled:false,\r\n                 theme:'red'\r\n                }\r\n        \u003c/script\u003e\r\n        \u003cscript type=\"text/javascript\" src=\"/template/global/topup/jquery.topup.packed.js\"\u003e\u003c/script\u003e\r\n        \u003cscript type=\"text/javascript\" src=\"/template/global/live.script.js\"\u003e\u003c/script\u003e\r\n\r\n\u003c/head\u003e\r\n\u003cbody\u003e\r\n\u003c!--  --\u003e\r\n\r\n\u003cdiv id=\"header\"\u003e\r\n        \u003cdiv\u003e\r\n                \u003cdiv\u003e\r\n                        \u003cspan\u003e\r\n                                \r\n                                \u003ca id=\"back\" class=\"off\"\u003e\u0026nbsp;\u003c/a\u003e\u003ca id=\"home\" class=\"off\"\u003e\u0026nbsp;\u003c/a\u003e\r\n                                \u003ca id=\"upload\"  class=\"off\" title=\"Upload files to this folder.\"\u003e\u0026nbsp;\u003c/a\u003e\r\n\r\n                                \u003ca id=\"delete\"  class=\"off\" title=\"Delete is disabled for this folder.\"\u003e\u0026nbsp;\u003c/a\u003e\r\n                                \u003ca id=\"login\" href=\"~login\" title=\"Click to Login\"\u003e\u0026nbsp;\u003c/a\u003e\r\n                                \r\n                        \u003c/span\u003e\r\n                \u003c/div\u003e\r\n        \u003c/div\u003e\r\n\u003c/div\u003e\r\n\u003cdiv id=\"content\"\u003e\r\n        \u003cdiv id=\"breadcrumbs\"\u003e\r\n                \u003cul id=\"controls\"\u003e\r\n                        \u003cli class=\"button dropdown\"\u003e\r\n                                \u003ca href=\"javascript:select('all');\"\u003eSelect\u003c/a\u003e\r\n                                \u003cul\u003e\r\n                                       \u003ca href=\"javascript:select('all');\"\u003e\u0026nbsp;- All\u003c/a\u003e\r\n                                       \u003ca href=\"javascript:select('none');\"\u003e\u0026nbsp;- None\u003c/a\u003e\r\n                                       \u003ca href=\"javascript:select('invert');\"\u003e\u0026nbsp;- Invert\u003c/a\u003e\r\n                                \u003c/ul\u003e\r\n                        \u003c/li\u003e\r\n                        \u003cli class=\"button dropdown\"\u003e\r\n                                \u003ca href=\"/?sort=n\"\u003eSort\u003c/a\u003e\r\n                                \u003cul\u003e\r\n                                         \r\n                                        \u003cli\u003e\u003ca  href=\"/?sort=t\"\u003e\u0026nbsp;- Age\u003c/a\u003e\u003c/li\u003e\r\n                                        \u003cli\u003e\u003ca  href=\"/?sort=n\"\u003e\u0026nbsp;- Name\u003c/a\u003e\u003c/li\u003e\r\n                                        \u003cli\u003e\u003ca  href=\"/?sort=s\"\u003e\u0026nbsp;- Size\u003c/a\u003e\u003c/li\u003e\r\n                                        \u003cli\u003e\u003ca  href=\"/?sort=d\"\u003e\u0026nbsp;- Hits\u003c/a\u003e\u003c/li\u003e\r\n                                        \u003cli\u003e\u003ca  href=\"/?sort=e\"\u003e\u0026nbsp;- Type\u003c/a\u003e\u003c/li\u003e\r\n                                \u003c/ul\u003e\r\n                        \u003c/li\u003e\r\n                \u003c/ul\u003e\r\n                Directory: \u0026nbsp;  \u003ca href=\"/\"\u003eHome\u003c/a\u003e\r\n                \r\n        \u003c/div\u003e\r\n\u003cdiv id=\"list\"\u003e\r\n                \u003cdiv class=\"clear\"\u003e\u003c/div\u003e\r\n                \r\n\r\n                \u003cdiv class=\"item folder \"\r\n         item-access=\"This item is protected.\"\r\n         item-added=\"02.02.2015 20:27:56\"\r\n         item-dl-count=\"4693748\"\r\n         item-comment=\"\"\u003e\r\n        \u003ca href=\"Login/\" title=\"Click to Enter\"\u003e\r\n                \u003cimg src=\"/template/red/images/icons/folder.gif\" alt=\"\"/\u003e\r\n                \r\n        \u003c/a\u003e\r\n        \u003cdiv\u003e\u003ca href=\"Login/\" title=\"Click to Enter\"\u003eLogin\u003c/a\u003e\u003cspan\u003e\u003c/span\u003e\u003c/div\u003e\r\n\u003c/div\u003e\r\n\r\n                \u003cdiv class=\"clear\"\u003e\u003c/div\u003e\r\n        \u003c/div\u003e\r\n        \u003cdiv id=\"footer\"\u003e\r\n        \u003cspan class=\"right\"\u003ePowered by Ultimate Pedo Archives\u003c/a\u003e ---\u003e \u003ca href=\"http://kdq2y44aaas2aiu4.onion\"\u003eRegister\u003c/a\u003e\u003c/span\u003e\r\n        \u003c/div\u003e\r\n\u003c/div\u003e\r\n\u003c/body\u003e\r\n\u003c/html\u003e\r\n\r\n","pageTitle":"UPA - Gallery/","responseHeaders":{"ACCEPT-RANGES":"bytes","CACHE-CONTROL":"no-cache, no-store, must-revalidate, max-age=-1","CONTENT-LENGTH":"4612","CONTENT-TYPE":"text/html","SET-COOKIE":"HFS_SID_=0.440087067196146; path=/; HttpOnly"},"bitcoinAddresses":null,"sshKey":"","ftpFingerprint":"","ftpBanner":"","smtpFingerprint":"","smtpBanner":""}
