{"hiddenService":"5i3gqg3jz7zs6x62.onion","webDetected":true,"sshDetected":false,"ricochetDetected":false,"ircDetected":false,"ftpDetected":false,"smtpDetected":false,"bitcoinDetected":false,"mongodbDetected":false,"vncDetected":false,"xmppDetected":false,"serverPoweredBy":"","serverVersion":"nginx/1.6.2","foundApacheModStatus":false,"relatedOnionServices":null,"relatedOnionDomains":null,"linkedSites":["github.com","utah.cryptoparty.i2p","getbootstrap.com","cryptopartyutah.org","www.w3.org"],"internalPages":["","5i3gqg3jz7zs6x62.onion"],"ipAddresses":null,"openDirectories":null,"exifImages":null,"interestingFiles":null,"pageReferencedDirectories":["/css","/css","js","js","/links","/presentations/2016/07/15/letsencrypttls","/slides","/files","http:/","/js","/js"],"pgpKeys":null,"hashes":["fbc72af54203db9ada7b3c74509aa8605f5c0ebe"],"snapshot":"\u003c!DOCTYPE html\u003e\n\u003chtml\u003e\n\n  \u003chead\u003e\n    \u003cmeta charset=\"utf-8\"\u003e\n    \u003cmeta http-equiv=\"X-UA-Compatible\" content=\"IE=edge\"\u003e\n    \u003cmeta name=\"viewport\" content=\"width=device-width, initial-scale=1\"\u003e\n    \u003ctitle\u003eCryptoParty - Utah\u003c/title\u003e\n    \u003cmeta name=\"description\" content=\"Party like it's December 31st, 1983\"\u003e\n    \u003clink rel=\"canonical\" href=\"http://cryptopartyutah.org/\"\u003e\n\n    \u003clink rel=\"icon\" type=\"image/png\" href=\"/favicon.png\" /\u003e\n\n    \u003clink rel=\"stylesheet\" href=\"/css/cryptoparty.css\"\u003e\n    \u003clink rel=\"stylesheet\" href=\"/css/bootstrap.min.css\"\u003e\n    \u003c!-- HTML5 shim and Respond.js IE8 support of HTML5 elements and media queries --\u003e\n\t\u003c!--[if lt IE 9]\u003e\n\t    \u003cscript src=\"js/html5shiv.js\"\u003e\u003c/script\u003e\n\t    \u003cscript src=\"js/respond.min.js\"\u003e\u003c/script\u003e\n\t\u003c![endif]--\u003e\n\u003c/head\u003e\n\n\n    \u003cbody\u003e\n      \u003cnav class=\"navbar navbar-inverse\" role=\"navigation\"\u003e\n  \u003cdiv class=\"navbar-header\"\u003e\n    \u003cbutton type=\"button\" class=\"navbar-toggle\" data-toggle=\"collapse\" data-target=\".navbar-collapse\"\u003e\n        \u003cspan class=\"sr-only\"\u003eToggle navigation\u003c/span\u003e\n        \u003cspan class=\"icon-bar\"\u003e\u003c/span\u003e\n        \u003cspan class=\"icon-bar\"\u003e\u003c/span\u003e\n        \u003cspan class=\"icon-bar\"\u003e\u003c/span\u003e\n    \u003c/button\u003e\n    \u003ca class=\"navbar-brand\" href=\"/\"\u003e\n      \u003csvg version=\"1.1\" xmlns=\"http://www.w3.org/2000/svg\" xmlns:xlink=\"http://www.w3.org/1999/xlink\" x=\"0\" y=\"0\" width=\"15\" height=\"15\" viewBox=\"0, 0, 255.555, 261.395\"\u003e\n        \u003cg id=\"Layer_1\" transform=\"translate(-0.207, 27.527)\"\u003e\n          \u003cg\u003e\n            \u003cpath d=\"M61.707,104.953 C61.707,65.752 91.604,33.973 128.484,33.973\" fill-opacity=\"0\" stroke=\"#FFF\" stroke-width=\"30\"/\u003e\n            \u003cpath d=\"M128.484,33.973 C165.364,33.973 195.262,65.752 195.262,104.953\" fill-opacity=\"0\" stroke=\"#FFF\" stroke-width=\"30\"/\u003e\n          \u003c/g\u003e\n          \u003cg\u003e\n            \u003cpath d=\"M223.221,113.953 C228.063,113.953 231.988,119.326 231.988,125.953 L231.988,221.367 C231.988,227.995 228.063,233.367 223.221,233.367 L33.748,233.367 C28.906,233.367 24.98,227.995 24.98,221.367 L24.98,125.953 C24.98,119.326 28.906,113.953 33.748,113.953 z M88.952,138.484 C69.516,138.484 53.776,154.224 53.776,173.66 C53.776,193.097 69.516,208.836 88.952,208.836 C102.02,208.836 113.404,201.552 119.407,190.9 L133.426,190.754 L144.443,179.663 L152.789,188.155 L161.245,179.663 L169.663,188.155 L178.155,179.517 L186.977,188.375 L187.196,188.302 L201.911,173.367 C203.558,171.647 203.705,170.073 201.838,168.206 L189.978,156.2 L119.187,156.054 C113.038,145.622 101.873,138.484 88.952,138.484 z M73.579,163.631 C78.813,163.631 83.023,167.95 83.023,173.074 C83.023,178.309 78.813,182.591 73.579,182.591 C68.308,182.591 64.135,178.309 64.135,173.074 C64.135,167.95 68.345,163.631 73.579,163.631 z\" fill=\"#FFF\"/\u003e\n            \u003cpath d=\"M223.221,113.953 C228.063,113.953 231.988,119.326 231.988,125.953 L231.988,221.367 C231.988,227.995 228.063,233.367 223.221,233.367 L33.748,233.367 C28.906,233.367 24.98,227.995 24.98,221.367 L24.98,125.953 C24.98,119.326 28.906,113.953 33.748,113.953 z M88.952,138.484 C69.516,138.484 53.776,154.224 53.776,173.66 C53.776,193.097 69.516,208.836 88.952,208.836 C102.02,208.836 113.404,201.552 119.407,190.9 L133.426,190.754 L144.443,179.663 L152.789,188.155 L161.245,179.663 L169.663,188.155 L178.155,179.517 L186.977,188.375 L187.196,188.302 L201.911,173.367 C203.558,171.647 203.705,170.073 201.838,168.206 L189.978,156.2 L119.187,156.054 C113.038,145.622 101.873,138.484 88.952,138.484 z M73.579,163.631 C78.813,163.631 83.023,167.95 83.023,173.074 C83.023,178.309 78.813,182.591 73.579,182.591 C68.308,182.591 64.135,178.309 64.135,173.074 C64.135,167.95 68.345,163.631 73.579,163.631 z\" fill-opacity=\"0\" stroke=\"#FFF\" stroke-width=\"1\"/\u003e\n          \u003c/g\u003e\n      \u003c/g\u003e\n      \u003c/svg\u003e\n      CryptoParty - Utah\n    \u003c/a\u003e\n  \u003c/div\u003e \n  \u003cdiv class=\"navbar-collapse collapse\"\u003e\n    \u003cul class=\"nav navbar-nav\"\u003e\n      \u003cli\u003e\u003ca href=\"/links/\"\u003eLinks\u003c/a\u003e\u003c/li\u003e\n    \u003c/ul\u003e\n  \u003c/div\u003e\n\u003c/nav\u003e\n\n      \u003cdiv id=\"content\"\u003e\n        \u003cdiv class=\"container\"\u003e\n          \u003cdiv class=\"home\"\u003e\n\n  \n  \u003cdiv class=\"row\"\u003e\n\n    \u003cheader class=\"post-header\"\u003e\n      \u003ca class=\"post-link\" href=\"/presentations/2016/07/15/letsencrypttls/\"\u003e\u003ch1\u003eLets Encrypt and TLS Optimization\u003c/h1\u003e\u003c/a\u003e\n      \u003cp class=\"meta\"\u003eJul 15, 2016\u003c/p\u003e\n    \u003c/header\u003e\n      \n    \u003carticle class=\"post-content\"\u003e\n      \u003cp\u003eHere are the slides for my presentation at OpenWest 2016 - ‘Using Let’s Encrypt and Optimizing TLS’\u003c/p\u003e\n\n\u003cp\u003e\u003ca href=\"/slides/letsencrypt_optimizingtls.pdf\"\u003eSlides\u003c/a\u003e\u003c/p\u003e\n\n\n    \u003c/article\u003e\n  \u003c/div\u003e\n  \n\n  \n  \u003cdiv class=\"row\"\u003e\n    \u003chr/\u003e\n    \n    \u003cnav\u003e\n      \u003cul class=\"pager\"\u003e\n\t\n\t\n\t  \u003cli\u003e\u003ca href=\"/page2\"\u003e\n\t    Next \u003cspan class=\"glyphicon glyphicon-triangle-right\" aria-hidden=\"true\"\u003e\u003c/span\u003e\n\t  \u003c/a\u003e\u003c/li\u003e\n\t\n      \u003c/ul\u003e\n    \u003c/nav\u003e\n\n  \u003c/div\u003e\n  \n\u003c/div\u003e\n\n        \u003c/div\u003e\n      \u003c/div\u003e\n\n      \u003cdiv id=\"about\"\u003e\n  \u003cdiv class=\"container\"\u003e\n    \u003cdiv class=\"row\"\u003e\n      \u003cdiv class=\"col-12\"\u003e\n\t    \u003ch2\u003eAbout\u003c/h2\u003e\n\t    \u003cp\u003eWe are focused on online privacy advocacy and education.  We welcome anyone interested, or concerned with how technology impacts privacy.  We plan on providing education and support for using cryptography and good security practices. \u003c/p\u003e\n\t  \u003c/div\u003e\n\t\u003c/div\u003e\n  \u003c/div\u003e\n\u003c/div\u003e\n      \u003cfooter\u003e\n  \u003cdiv class=\"container\"\u003e\n    \u003cdiv class=\"row\"\u003e\n\n      \u003cdiv class=\"col-sm-4\"\u003e\n        \u003ch4\u003eContact\u003c/h4\u003e\n        \u003cul class=\"list-unstyled\"\u003e\n          \u003cli\u003e\u003ca href=\"mailto:cdhop@disquietingcandor.net\"\u003ecdhop@disquietingcandor.net\u003c/a\u003e\u003c/li\u003e\n          \u003cli\u003e\u003ca href=\"/files/C8670D8D.asc\"\u003eGPG/PGP Key\u003c/a\u003e\u003c/li\u003e\n        \u003c/ul\u003e\n      \u003c/div\u003e\n\n      \u003cdiv class=\"col-sm-2\"\u003e\n        \u003ch4\u003eResources\u003c/h4\u003e\n        \u003cul class=\"list-unstyled\"\u003e\n          \u003cli\u003e\n            \u003ca href=\"https://github.com/cdhop/cryptopartyutah\"\u003e\n              \u003cspan class=\"icon github\"\u003e\n                \u003csvg version=\"1.1\" width=\"16px\" height=\"16px\" class=\"github-icon-svg\" xmlns=\"http://www.w3.org/2000/svg\" xmlns:xlink=\"http://www.w3.org/1999/xlink\" x=\"0px\" y=\"0px\"\n                   viewBox=\"0 0 16 16\" enable-background=\"new 0 0 16 16\" xml:space=\"preserve\"\u003e\n                  \u003cpath fill-rule=\"evenodd\" clip-rule=\"evenodd\" fill=\"#000\" d=\"M7.999,0.431c-4.285,0-7.76,3.474-7.76,7.761\n                  c0,3.428,2.223,6.337,5.307,7.363c0.388,0.071,0.53-0.168,0.53-0.374c0-0.184-0.007-0.672-0.01-1.32\n                  c-2.159,0.469-2.614-1.04-2.614-1.04c-0.353-0.896-0.862-1.135-0.862-1.135c-0.705-0.481,0.053-0.472,0.053-0.472\n                  c0.779,0.055,1.189,0.8,1.189,0.8c0.692,1.186,1.816,0.843,2.258,0.645c0.071-0.502,0.271-0.843,0.493-1.037\n                  C4.86,11.425,3.049,10.76,3.049,7.786c0-0.847,0.302-1.54,0.799-2.082C3.768,5.507,3.501,4.718,3.924,3.65\n                  c0,0,0.652-0.209,2.134,0.796C6.677,4.273,7.34,4.187,8,4.184c0.659,0.003,1.323,0.089,1.943,0.261\n                  c1.482-1.004,2.132-0.796,2.132-0.796c0.423,1.068,0.157,1.857,0.077,2.054c0.497,0.542,0.798,1.235,0.798,2.082\n                  c0,2.981-1.814,3.637-3.543,3.829c0.279,0.24,0.527,0.713,0.527,1.437c0,1.037-0.01,1.874-0.01,2.129\n                  c0,0.208,0.14,0.449,0.534,0.373c3.081-1.028,5.302-3.935,5.302-7.362C15.76,3.906,12.285,0.431,7.999,0.431z\"/\u003e\n                \u003c/svg\u003e\n              \u003c/span\u003e\n              \u003cspan class=\"username\"\u003eGitHub\u003c/span\u003e\n            \u003c/a\u003e\n          \u003c/li\u003e\n          \u003cli\u003e\n            \u003ca href=\"/feed.xml\"\u003e\n              \u003cspan\u003e\n                \u003csvg xmlns=\"http://www.w3.org/2000/svg\" version=\"1.1\" width=\"16px\" height=\"16px\" id=\"RSSicon\" viewBox=\"0 0 256 256\"\u003e\n                  \u003cdefs\u003e\n                    \u003clinearGradient x1=\"0.085\" y1=\"0.085\" x2=\"0.915\" y2=\"0.915\" id=\"RSSg\"\u003e\n                    \u003cstop  offset=\"0.0\" stop-color=\"#E3702D\"/\u003e\u003cstop  offset=\"0.1071\" stop-color=\"#EA7D31\"/\u003e\n                    \u003cstop  offset=\"0.3503\" stop-color=\"#F69537\"/\u003e\u003cstop  offset=\"0.5\" stop-color=\"#FB9E3A\"/\u003e\n                    \u003cstop  offset=\"0.7016\" stop-color=\"#EA7C31\"/\u003e\u003cstop  offset=\"0.8866\" stop-color=\"#DE642B\"/\u003e\n                    \u003cstop  offset=\"1.0\" stop-color=\"#D95B29\"/\u003e\n                    \u003c/linearGradient\u003e\n                  \u003c/defs\u003e\n                  \u003crect width=\"256\" height=\"256\" rx=\"55\" ry=\"55\" x=\"0\"  y=\"0\"  fill=\"#CC5D15\"/\u003e\n                  \u003crect width=\"246\" height=\"246\" rx=\"50\" ry=\"50\" x=\"5\"  y=\"5\"  fill=\"#F49C52\"/\u003e\n                  \u003crect width=\"236\" height=\"236\" rx=\"47\" ry=\"47\" x=\"10\" y=\"10\" fill=\"url(#RSSg)\"/\u003e\n                  \u003ccircle cx=\"68\" cy=\"189\" r=\"24\" fill=\"#FFF\"/\u003e\n                  \u003cpath d=\"M160 213h-34a82 82 0 0 0 -82 -82v-34a116 116 0 0 1 116 116z\" fill=\"#FFF\"/\u003e\n                  \u003cpath d=\"M184 213A140 140 0 0 0 44 73 V 38a175 175 0 0 1 175 175z\" fill=\"#FFF\"/\u003e\n                \u003c/svg\u003e\n              \u003c/span\u003e\n              \u003cspan\u003eRSS\u003c/span\u003e\n            \u003c/a\u003e\n          \u003c/li\u003e\n        \u003c/ul\u003e\n      \u003c/div\u003e\n\n      \u003cdiv class=\"col-sm-6\"\u003e\n        \u003ch4\u003eDarknet\u003c/h4\u003e\n        \u003cul class=\"list-unstyled\"\u003e\n          \u003cli\u003eHidden Service (Tor): \u003ca href=\"http://5i3gqg3jz7zs6x62.onion\"\u003e5i3gqg3jz7zs6x62.onion\u003c/a\u003e\u003c/li\u003e\n          \u003cli\u003eEepsite (i2p): \u003ca href=\"http://utah.cryptoparty.i2p\"\u003eutah.cryptoparty.i2p\u003c/a\u003e\u003c/li\u003e\n        \u003c/ul\u003e\n      \u003c/div\u003e\n\n    \u003c/div\u003e\n  \u003c/div\u003e\n\u003c/footer\u003e\n\n      \u003cscript src=\"/js/jquery.min.js\"\u003e\u003c/script\u003e\n      \u003cscript src=\"/js/bootstrap.min.js\"\u003e\u003c/script\u003e\n    \u003c/body\u003e\n\u003c/html\u003e","pageTitle":"CryptoParty - Utah","responseHeaders":{"CONNECTION":"keep-alive","CONTENT-TYPE":"text/html","DATE":"Thu, 21 Jul 2016 23:58:54 GMT","LAST-MODIFIED":"Sat, 16 Jul 2016 02:07:21 GMT","SERVER":"nginx/1.6.2"},"bitcoinAddresses":null,"sshKey":"","ftpFingerprint":"","ftpBanner":"","smtpFingerprint":"","smtpBanner":""}
