{"hiddenService":"abbujjh5vqtq77wg.onion","webDetected":true,"sshDetected":false,"ricochetDetected":false,"ircDetected":false,"ftpDetected":false,"smtpDetected":false,"bitcoinDetected":false,"mongodbDetected":false,"vncDetected":false,"xmppDetected":false,"serverPoweredBy":"","serverVersion":"Apache","foundApacheModStatus":false,"relatedOnionServices":null,"relatedOnionDomains":null,"linkedSites":["www.w3.org"],"internalPages":[""],"ipAddresses":null,"openDirectories":null,"exifImages":null,"interestingFiles":null,"pageReferencedDirectories":["products/cat/100","products/cat/200","products/cat/300"],"pgpKeys":null,"hashes":["f72600ed6ec48b0ac56f1c44d5728615b1279906"],"snapshot":"\u003c!DOCTYPE HTML PUBLIC \"-//W3C//DTD HTML 4.01 Transitional//EN\" \"http://www.w3.org/TR/html4/loose.dtd\"\u003e\r\n\u003chtml\u003e\r\n\u003chead\u003e\r\n\u003cmeta http-equiv=\"Content-type\" content=\"text/html; charset=utf-8\"\u003e\r\n\u003cmeta name=\"description\" content=\"Onion Identity Store - buy european fake ids, fake passports with Bitcoin\"/\u003e\r\n\u003clink rel=\"icon\" type=\"image/icon\" href=\"favicon.ico\"\u003e\t\r\n\u003clink rel=\"shortcut icon\" type=\"image/icon\" href=\"favicon.ico\"\u003e\r\n\u003ctitle\u003eOnion Identity Services - Get your fake passport and a new identity today\u003c/title\u003e\r\n\u003cstyle type=\"text/css\"\u003e\r\nbody{background-color: #E9E9E9;\r\n\tbackground-image:url(background.png);\r\n\tfont:14px Arial,Sans-serif;\r\n\tmargin:0;\r\n\tpadding:0;}\r\n\r\nimg {border:0;}\r\n\r\n.floatimg {padding-bottom:5px; padding-right:20px;}\r\n\r\nh3 {color:#333; font: bold 28px/1em HelveticaNeue, Arial, sans-serif; margin: 5px 0 20px 2px;}\r\n\r\n#header {\r\n\twidth:892px;\r\n\theight:82px;\r\n\tposition: absolute;\r\n\tleft: 50%;\r\n\tmargin-left:-446px;\r\n\tmargin-top: -100px;\r\n\tmargin-bottom: 0px;\r\n\tz-index:4;\r\n\tbackground-color: #464646;\r\n    -webkit-border-radius: 0 0 7px 7px;\r\n\t-moz-border-radius: 0 0 7px 7px;\r\n\tborder-radius: 0 0 7px 7px;}\r\n\r\n#logo { height:82px;width:892px;}\r\n\r\n#logo img{\r\n    -webkit-border-radius: 0 0 7px 7px;\r\n\t-moz-border-radius: 0 0 7px 7px;\r\n\tborder-radius: 0 0 7px 7px;}\r\n\r\n/* Menu */\r\n.menu, .menu ul {margin:5px 0;padding:0;list-style:none;}\r\n.menu li, .menu ul a {position:relative;}\r\n.menu \u003e li {float:left;}\r\n.menu \u003e li.floatr {float:right;}\r\n.menu li \u003e a {display:block;}\r\n.menu ul {position:absolute; display:none; width:125px;}\r\n.menu ul ul {top:0; left:125px;}\r\n.menu \u003e li.floatr \u003e ul {right:0;}\r\n.menu \u003e li.floatr \u003e ul ul {left:-125px;}\r\n.menu li:hover \u003e ul {display:block;}\r\n\r\n.menu {\r\n\theight:32px;\r\n\tborder:1px solid #b2b2b2;\r\n\tfont-family:Arial, Helvetica, sans-serif;\r\n\tbackground-color:#d4d4d4;\r\n\tbackground-image:-webkit-linear-gradient(top, #e0e0e0, #c8c8c8);\r\n\tbackground-image:-moz-linear-gradient(top, #e0e0e0, #c8c8c8);\r\n\tbackground-image:-o-linear-gradient(top, #e0e0e0, #c8c8c8);\r\n\tbackground-image:-ms-linear-gradient(top, #e0e0e0, #c8c8c8);\r\n\tbackground-image:linear-gradient(top, #e0e0e0, #c8c8c8);\r\n\t-webkit-border-radius:3px;\r\n\t-moz-border-radius:3px;\r\n\tborder-radius:3px;\r\n\t-webkit-box-shadow:inset 0 1px #f4f4f4, inset 0 -1px #b3b3b3, 0 1px 3px #ddd;\r\n\t-moz-box-shadow:inset 0 1px #f4f4f4, inset 0 -1px #b3b3b3, 0 1px 3px #ddd;\r\n\tbox-shadow:inset 0 1px #f4f4f4, inset 0 -1px #b3b3b3, 0 1px 3px #ddd;}\r\n\r\n.menu a {text-decoration:none;}\r\n.menu \u003e li \u003e a {\r\n\tcolor:#444;\r\n\tfont-weight:bold;\r\n\tfont-size:12px;\r\n\tline-height:16px;\r\n\ttext-shadow:0 1px #f8f8f8;\r\n\tpadding:8px 12px 8px;}\r\n.menu \u003e li:hover \u003e a {\r\n\tbackground-color:#fff;\r\n\tbackground-image:-webkit-linear-gradient(top, #f5f5f5, #fff);\r\n\tbackground-image:-moz-linear-gradient(top, #f5f5f5, #fff);\r\n\tbackground-image:-o-linear-gradient(top, #f5f5f5, #fff);\r\n\tbackground-image:-ms-linear-gradient(top, #f5f5f5, #fff);\r\n\tbackground-image:linear-gradient(top, #f5f5f5, #fff);\t\r\n\t-webkit-box-shadow:inset 0 3px #eee;\r\n\t-moz-box-shadow:inset 0 3px #eee;\r\n\tbox-shadow:inset 0 3px #eee;\t\r\n\tborder-left:none;\r\n\tpadding-left:13px;}\r\n\r\n.menu \u003e li {border-right:1px solid #bbb;border-right:1px solid rgba(10, 10, 10, .1);}\r\n.menu \u003e li \u003e a {border-left:1px solid #e3e3e3;border-left:1px solid rgba(255, 255, 255, .35);}\r\n.menu \u003e li.floatr {border-right:none;border-left:1px solid #bbb;border-left:1px solid rgba(10, 10, 10, .1);}\r\n\r\n.menu \u003e li \u003e a .bubble-top {\r\n\tposition:absolute;\r\n\tfont-size:11px;\r\n\tline-height:14px;\r\n\tcolor:#fff;\r\n\tpadding:0 3px;\r\n\tright:4px;\r\n\ttop:-8px;\r\n\ttext-shadow:none;\r\n\tborder:1px solid #a00000;\r\n\t-webkit-border-radius:3px;\r\n\t-moz-border-radius:3px;\r\n\tborder-radius:2px;\r\n\tbackground-color: #df0a0a;\r\n\tbackground-image: -webkit-linear-gradient(top, #f26870, #ec0e23);\r\n\tbackground-image: -moz-linear-gradient(top, #f26870, #ec0e23);\r\n\tbackground-image: -o-linear-gradient(top, #f26870, #ec0e23);\r\n\tbackground-image: -ms-linear-gradient(top, #f26870, #ec0e23);\r\n\tbackground-image: linear-gradient(top, #f26870, #ec0e23);\r\n\t-webkit-box-shadow:inset 0 1px #ffa7a7;\r\n\t-moz-box-shadow:inset 0 1px #ffa7a7;\r\n\tbox-shadow:inset 0 1px #ffa7a7;}\r\n\r\n/* End of Menu */\r\n\r\n#main\r\n{background:#FFFFFF;\r\n\tz-index:2;\r\n\tcolor:#333;\r\n\tborder:1px solid #A8A8A8;\r\n\tborder-radius:5px;\r\n\tmargin:100px auto 10px;\r\n\tpadding:40px 20px 10px;\r\n\tposition:relative;\r\n\twidth:850px;\r\n\t-moz-box-shadow: 0px 0px 35px rgba(0,0,0,0.25);\r\n\t-webkit-box-shadow: 0px 0px 35px rgba(0,0,0,0.25);\r\n\tbox-shadow: 0px 0px 35px rgba(0,0,0,0.25)}\r\n\r\n.txt\r\n{\r\n\tborder:1px solid #B3B3B3;\r\n\theight:20px;\r\n\tmargin-bottom:7px;\r\n\tmargin-top:7px;\r\n\tpadding: 3px 0;\r\n\tpadding-left: 5px;\r\n\ttext-align:left;\r\n\tbackground: #fff;\r\n\toutline: none;\r\n\t-moz-border-radius:    5px;\r\n\t-webkit-border-radius: 5px;\r\n\tborder-radius:         5px;\r\n\t-moz-box-shadow:    inset 0 0 1px rgba(0, 0, 0, 0.5), 0 1px 0 rgba(255, 255, 255, 0.7);\r\n\t-webkit-box-shadow: inset 0 0 1px rgba(0, 0, 0, 0.5), 0 1px 0 rgba(255, 255, 255, 0.7);\r\n\tbox-shadow:         inset 0 0 1px rgba(0, 0, 0, 0.5), 0 1px 0 rgba(255, 255, 255, 0.7);}\r\n\r\n.txt.form{text-align: center;padding-left: 0;}\r\n\r\n.txt:focus\r\n{\r\n\tborder: 1px solid #7fbbf9;\r\n\t-moz-box-shadow:    inset 0 0 1px rgba(0, 0, 0, 0.5), 0 0 3px #7fbbf9;\r\n\t-webkit-box-shadow: inset 0 0 1px rgba(0, 0, 0, 0.5), 0 0 3px #7fbbf9;\r\n\tbox-shadow:         inset 0 0 1px rgba(0, 0, 0, 0.5), 0 0 3px #7fbbf9;\r\n\t-moz-box-shadow:0 0 10px rgba(0,0,0,0.5);\r\n\t-webkit-box-shadow:0 0 10px rgba(0,0,0,0.5);\r\n\tbox-shadow:0 0 10px rgba(0,0,0,0.5);}\r\n\r\na:link{color:#333;font-weight:bold;text-decoration:none;}\r\n\r\na:hover {color:#000;}\r\n\r\ntextarea{\r\n\tborder:2px solid #B3B3B3;\r\n\tborder-radius:5px;\r\n\t-moz-box-shadow:    inset 0 0 3px rgba(0, 0, 0, 0.25), 0 3px 0 rgba(255, 255, 255, 0.5);\r\n\t-webkit-box-shadow: inset 0 0 3px rgba(0, 0, 0, 0.25), 0 3px 0 rgba(255, 255, 255, 0.5);\r\n\tbox-shadow:         inset 0 0 3px rgba(0, 0, 0, 0.25), 0 3px 0 rgba(255, 255, 255, 0.5);\r\n\tpadding:5px;}\r\n\r\ntextarea:focus{\r\n\tborder: 2px solid #7fbbf9;\r\n\t-moz-box-shadow:    inset 0 0 3px rgba(0, 0, 0, 0.5), 0 0 3px #7fbbf9;\r\n\t-webkit-box-shadow: inset 0 0 3px rgba(0, 0, 0, 0.5), 0 0 3px #7fbbf9;\r\n\tbox-shadow:         inset 0 0 3px rgba(0, 0, 0, 0.5), 0 0 3px #7fbbf9;\r\n\t-moz-box-shadow:0 0 10px rgba(0,0,0,0.5);\r\n\t-webkit-box-shadow:0 0 10px rgba(0,0,0,0.5);\r\n\tbox-shadow:0 0 10px rgba(0,0,0,0.5);}\r\n\r\ntable {\r\n    border-spacing: 0; \r\n\tborder-color: gray;}\r\n\r\n.table1 th{\r\n\tfont:800 18px Arial,sans-serif;\r\n\ttext-align: left;\r\n\tpadding: 10px;\r\n\tbackground-color:#333;\r\n\tcolor:#FFF;}\r\n\r\n.table1 th:first-child {\r\n    -moz-border-radius: 6px 0 0 0;\r\n    -webkit-border-radius: 6px 0 0 0;\r\n    border-radius: 6px 0 0 0;}\r\n\r\n.table1 th:last-child {\r\n    -moz-border-radius: 0 6px 0 0;\r\n    -webkit-border-radius: 0 6px 0 0;\r\n    border-radius: 0 6px 0 0;}\r\n\r\n.table1 th:only-child{\r\n    -moz-border-radius: 6px 6px 0 0;\r\n    -webkit-border-radius: 6px 6px 0 0;\r\n    border-radius: 6px 6px 0 0;}\r\n\r\n.table1 td{\r\n\ttext-align: left;\r\n\tpadding: 5px 10px;\r\n\tborder-left: 2px solid #ffffff;}\r\n\r\n.table1 tbody tr:nth-child(odd) {\r\n    background: #f5f5f5;\r\n    -webkit-box-shadow: 0 1px 0 rgba(255,255,255,.8) inset; \r\n    -moz-box-shadow:0 1px 0 rgba(255,255,255,.8) inset;  \r\n    box-shadow: 0 1px 0 rgba(255,255,255,.8) inset; }\r\n\r\ninput.checkb {margin-top:15px;}\r\n\r\nhr{border:1px solid #DCDFE4;}\r\n\r\n/*Buttons */\r\n\r\n.buttn{\r\n\tdisplay: inline-block;\r\n\ttext-decoration: none;\r\n\toutline: none;\r\n\tcursor: pointer;\r\n\tfont: bold 14px/1em HelveticaNeue, Arial, sans-serif;\r\n\tpadding: 6px 10px;\r\n\tborder: 1px solid #dedede;\r\n\t-webkit-border-radius: 4px;\r\n\t-moz-border-radius: 4px;\r\n\tborder-radius: 4px;\r\n\tbackground: #377ad0;\r\n\tbackground: -webkit-gradient(linear, left top, left bottom, from(#52a8e8), to(#377ad0));\r\n\tbackground: -moz-linear-gradient(top, #52a8e8, #377ad0);\r\n\tborder-color: #4081af #2e69a3 #20559a;\r\n\tcolor: #fff !important;\r\n\ttext-shadow: 0 1px 1px #4081af;\r\n\t-webkit-box-shadow: 0 1px 2px #d6d6d6, inset 0 1px 1px #72b9eb;\r\n\t-moz-box-shadow: 0 1px 2px #d6d6d6, inset 0 1px 1px #72b9eb;\r\n\tbox-shadow: 0 1px 2px #d6d6d6, inset 0 1px 1px #72b9eb;}\r\n\r\ninput.buttn, .buttn{\r\n\t*width: auto; /* IE7 Fix */\r\n\t*overflow: visible; /* IE7 Fix */}\r\n\r\n.buttn img {border: none;vertical-align: bottom;}\r\n\r\n.buttn:hover, .buttn:focus{\r\n\tbackground: #206bcb;\r\n\tbackground: -webkit-gradient(linear, left top, left bottom, from(#3e9ee5), to(#206bcb));\r\n\tbackground: -moz-linear-gradient(top, #3e9ee5, #206bcb);\r\n\tborder-color: #2a73a6 #165899 #07428f;\r\n\t-webkit-box-shadow: 0 1px 0 0 #fff, inset 0 1px 0 0 #62b1e9;\r\n\t-moz-box-shadow: 0 1px 0 0 #fff, inset 0 1px 0 0 #62b1e9;\r\n\tbox-shadow: 0 1px 0 0 #fff, inset 0 1px 0 0 #62b1e9;}\r\n.buttn:active{\r\n\tbackground: #3282d3;\r\n\tborder-color: #154c8c #154c8c #0e408e;\r\n\ttext-shadow: 0 -1px 1px #1d62ab;\r\n\t-webkit-box-shadow: 0 1px 0 0 #fff, inset 0 0 6px 3px #1657b5;\r\n\t-moz-box-shadow: 0 1px 0 0 #fff, inset 0 0 6px 3px #1657b5;\r\n\tbox-shadow: 0 1px 0 0 #fff, inset 0 0 6px 3px #1657b5;}\r\n\r\n.footer{\r\n\tborder-top: solid 1px #525252;\r\n\tpadding: 5px;\r\n\ttext-align: center;\r\n\tfont-weight: bold;\r\n\tfont-size: 12px;}\r\n\r\n#checkout {font-size:40px;}\r\n\r\n#warning {font-weight:bold; color:red;}\r\n\u003c/style\u003e\r\n\u003c/head\u003e\r\n\u003cbody\u003e\r\n\u003cdiv id=\"header\"\u003e\r\n\u003cdiv id=\"logo\"\u003e\u003ca href=\"index.php\"\u003e\u003cimg src=\"logo.png\" alt=\"Onion Identity Services - Get your fake passport and a new identity today\"\u003e\u003c/a\u003e\u003c/div\u003e\r\n\u003cul class=\"menu\" id=\"menu\"\u003e\r\n\t\u003cli\u003e\u003ca href=\"index.php\" title=\"Products\"\u003eProducts\u003c/a\u003e\u003c/li\u003e\r\n\t\u003cli\u003e\u003ca href=\"info.php\" title=\"Information about the shop\"\u003eInfo\u003c/a\u003e\u003c/li\u003e\r\n\t\u003cli class=\"floatr\"\u003e\u003ca href=\"register.php\" title=\"Registration\"\u003eRegistration\u003c/a\u003e\u003c/li\u003e\r\n\t\u003cli class=\"floatr\"\u003e\u003ca href=\"login.php\" title=\"Login\"\u003eLogin\u003c/a\u003e\u003c/li\u003e\r\n\u003c/ul\u003e\r\n\u003c/div\u003e\r\n\u003cdiv id=\"main\"\u003e\r\n\r\n\r\n\u003cbr\u003e\u003ch2\u003eOrder Process:\u003c/h2\u003e\u003cbr\u003e\r\nAfter buying an ID or passport send us a message with your age and gender so we can find a matching dataset, alternatively you can provide a dataset (name, age, gender, size etc).\r\nWe will also need a biometric photo in high quality and signature scanned, we will give more instructions after your purchase.\u003cbr\u003e\r\n\u003cbr\u003e\u003ch3\u003ePassports\u003c/h3\u003e\u003cimg src=\"products/cat/100/image.jpg\" class=floatimg style=\"float:left\" alt=\"\"\u003e\u003cbr\u003e\u003cbr\u003e\u003cbr\u003e\u003cbr\u003e\u003cbr\u003e\u003cbr\u003e\u003cbr\u003e\u003cbr\u003e\u003cbr\u003e\u003cbr\u003e\u003cbr\u003e\u003cbr\u003e\u003cbr\u003e\u003cbr\u003e\u003cbr\u003e\u003cbr\u003e\u003cbr\u003e\u003cbr\u003e\u003cbr\u003e\u003cbr\u003e\u003ctable class=\"table1\"\u003e\r\n\u003cthead\u003e\r\n\u003ctr\u003e\r\n\u003cth\u003eProduct\u003c/th\u003e\u003cth\u003ePrice\u003c/th\u003e\u003cth\u003eQuantity\u003c/th\u003e\r\n\u003c/tr\u003e\r\n\u003c/thead\u003e\r\n\u003ctbody\u003e\r\n\u003ctr\u003e\r\n\u003ctd\u003eLithuanian Passport\u003c/td\u003e\u003ctd\u003e2650 EUR = 4.357 \u0026#3647;\u003c/td\u003e\u003ctd\u003e\r\n\u003cform name=\"cart\" method=\"post\" action=\"cart.php\"\u003e\r\n\u003cinput value=\"100\" type=\"hidden\" name=\"id\"\u003e\r\n\u003cinput value=\"add\" type=\"hidden\" name=\"action\"\u003e\r\n\u003cinput value=\"1\" type=\"text\" class=\"txt\" name=\"menge\" size=\"2\"\u003e X \u003cinput type=\"submit\" class=\"buttn\" value=\"Buy now\"\u003e\u003c/form\u003e\u003c/td\u003e\r\n\u003c/tr\u003e\r\n\u003ctr\u003e\r\n\u003ctd\u003eNetherlands Passport\u003c/td\u003e\u003ctd\u003e3150 EUR = 5.179 \u0026#3647;\u003c/td\u003e\u003ctd\u003e\r\n\u003cform name=\"cart\" method=\"post\" action=\"cart.php\"\u003e\r\n\u003cinput value=\"101\" type=\"hidden\" name=\"id\"\u003e\r\n\u003cinput value=\"add\" type=\"hidden\" name=\"action\"\u003e\r\n\u003cinput value=\"1\" type=\"text\" class=\"txt\" name=\"menge\" size=\"2\"\u003e X \u003cinput type=\"submit\" class=\"buttn\" value=\"Buy now\"\u003e\u003c/form\u003e\u003c/td\u003e\r\n\u003c/tr\u003e\r\n\u003ctr\u003e\r\n\u003ctd\u003eDenmark Passport\u003c/td\u003e\u003ctd\u003e3150 EUR = 5.179 \u0026#3647;\u003c/td\u003e\u003ctd\u003e\r\n\u003cform name=\"cart\" method=\"post\" action=\"cart.php\"\u003e\r\n\u003cinput value=\"102\" type=\"hidden\" name=\"id\"\u003e\r\n\u003cinput value=\"add\" type=\"hidden\" name=\"action\"\u003e\r\n\u003cinput value=\"1\" type=\"text\" class=\"txt\" name=\"menge\" size=\"2\"\u003e X \u003cinput type=\"submit\" class=\"buttn\" value=\"Buy now\"\u003e\u003c/form\u003e\u003c/td\u003e\r\n\u003c/tr\u003e\r\n\u003ctr\u003e\r\n\u003ctd\u003eGreat Britain Passport\u003c/td\u003e\u003ctd\u003e4000 EUR = 6.576 \u0026#3647;\u003c/td\u003e\u003ctd\u003e\r\n\u003cform name=\"cart\" method=\"post\" action=\"cart.php\"\u003e\r\n\u003cinput value=\"103\" type=\"hidden\" name=\"id\"\u003e\r\n\u003cinput value=\"add\" type=\"hidden\" name=\"action\"\u003e\r\n\u003cinput value=\"1\" type=\"text\" class=\"txt\" name=\"menge\" size=\"2\"\u003e X \u003cinput type=\"submit\" class=\"buttn\" value=\"Buy now\"\u003e\u003c/form\u003e\u003c/td\u003e\r\n\u003c/tr\u003e\r\n\u003ctr\u003e\r\n\u003ctd\u003eCanada Passport\u003c/td\u003e\u003ctd\u003e2500 EUR = 4.110 \u0026#3647;\u003c/td\u003e\u003ctd\u003e\r\n\u003cform name=\"cart\" method=\"post\" action=\"cart.php\"\u003e\r\n\u003cinput value=\"104\" type=\"hidden\" name=\"id\"\u003e\r\n\u003cinput value=\"add\" type=\"hidden\" name=\"action\"\u003e\r\n\u003cinput value=\"1\" type=\"text\" class=\"txt\" name=\"menge\" size=\"2\"\u003e X \u003cinput type=\"submit\" class=\"buttn\" value=\"Buy now\"\u003e\u003c/form\u003e\u003c/td\u003e\r\n\u003c/tr\u003e\r\n\u003c/tbody\u003e\r\n\u003c/table\u003e\r\n\u003cbr\u003e\u003chr\u003e\u003ch3\u003eID Cards\u003c/h3\u003e\u003cimg src=\"products/cat/200/image.jpg\" class=floatimg style=\"float:left\" alt=\"\"\u003e\u003cbr\u003e\u003cbr\u003e\u003cbr\u003e\u003cbr\u003e\u003cbr\u003e\u003cbr\u003e\u003cbr\u003e\u003cbr\u003e\u003cbr\u003e\u003cbr\u003e\u003cbr\u003e\u003cbr\u003e\u003cbr\u003e\u003cbr\u003e\u003cbr\u003e\u003cbr\u003e\u003cbr\u003e\u003cbr\u003e\u003ctable class=\"table1\"\u003e\r\n\u003cthead\u003e\r\n\u003ctr\u003e\r\n\u003cth\u003eProduct\u003c/th\u003e\u003cth\u003ePrice\u003c/th\u003e\u003cth\u003eQuantity\u003c/th\u003e\r\n\u003c/tr\u003e\r\n\u003c/thead\u003e\r\n\u003ctbody\u003e\r\n\u003ctr\u003e\r\n\u003ctd\u003eCzech ID Card\u003c/td\u003e\u003ctd\u003e1000 EUR = 1.644 \u0026#3647;\u003c/td\u003e\u003ctd\u003e\r\n\u003cform name=\"cart\" method=\"post\" action=\"cart.php\"\u003e\r\n\u003cinput value=\"200\" type=\"hidden\" name=\"id\"\u003e\r\n\u003cinput value=\"add\" type=\"hidden\" name=\"action\"\u003e\r\n\u003cinput value=\"1\" type=\"text\" class=\"txt\" name=\"menge\" size=\"2\"\u003e X \u003cinput type=\"submit\" class=\"buttn\" value=\"Buy now\"\u003e\u003c/form\u003e\u003c/td\u003e\r\n\u003c/tr\u003e\r\n\u003ctr\u003e\r\n\u003ctd\u003eNetherlands ID Card\u003c/td\u003e\u003ctd\u003e1150 EUR = 1.891 \u0026#3647;\u003c/td\u003e\u003ctd\u003e\r\n\u003cform name=\"cart\" method=\"post\" action=\"cart.php\"\u003e\r\n\u003cinput value=\"201\" type=\"hidden\" name=\"id\"\u003e\r\n\u003cinput value=\"add\" type=\"hidden\" name=\"action\"\u003e\r\n\u003cinput value=\"1\" type=\"text\" class=\"txt\" name=\"menge\" size=\"2\"\u003e X \u003cinput type=\"submit\" class=\"buttn\" value=\"Buy now\"\u003e\u003c/form\u003e\u003c/td\u003e\r\n\u003c/tr\u003e\r\n\u003ctr\u003e\r\n\u003ctd\u003eDenmark ID Card\u003c/td\u003e\u003ctd\u003e1150 EUR = 1.891 \u0026#3647;\u003c/td\u003e\u003ctd\u003e\r\n\u003cform name=\"cart\" method=\"post\" action=\"cart.php\"\u003e\r\n\u003cinput value=\"202\" type=\"hidden\" name=\"id\"\u003e\r\n\u003cinput value=\"add\" type=\"hidden\" name=\"action\"\u003e\r\n\u003cinput value=\"1\" type=\"text\" class=\"txt\" name=\"menge\" size=\"2\"\u003e X \u003cinput type=\"submit\" class=\"buttn\" value=\"Buy now\"\u003e\u003c/form\u003e\u003c/td\u003e\r\n\u003c/tr\u003e\r\n\u003ctr\u003e\r\n\u003ctd\u003eFrench ID Card\u003c/td\u003e\u003ctd\u003e1150 EUR = 1.891 \u0026#3647;\u003c/td\u003e\u003ctd\u003e\r\n\u003cform name=\"cart\" method=\"post\" action=\"cart.php\"\u003e\r\n\u003cinput value=\"203\" type=\"hidden\" name=\"id\"\u003e\r\n\u003cinput value=\"add\" type=\"hidden\" name=\"action\"\u003e\r\n\u003cinput value=\"1\" type=\"text\" class=\"txt\" name=\"menge\" size=\"2\"\u003e X \u003cinput type=\"submit\" class=\"buttn\" value=\"Buy now\"\u003e\u003c/form\u003e\u003c/td\u003e\r\n\u003c/tr\u003e\r\n\u003ctr\u003e\r\n\u003ctd\u003eLithuanian ID Card\u003c/td\u003e\u003ctd\u003e1000 EUR = 1.644 \u0026#3647;\u003c/td\u003e\u003ctd\u003e\r\n\u003cform name=\"cart\" method=\"post\" action=\"cart.php\"\u003e\r\n\u003cinput value=\"206\" type=\"hidden\" name=\"id\"\u003e\r\n\u003cinput value=\"add\" type=\"hidden\" name=\"action\"\u003e\r\n\u003cinput value=\"1\" type=\"text\" class=\"txt\" name=\"menge\" size=\"2\"\u003e X \u003cinput type=\"submit\" class=\"buttn\" value=\"Buy now\"\u003e\u003c/form\u003e\u003c/td\u003e\r\n\u003c/tr\u003e\r\n\u003c/tbody\u003e\r\n\u003c/table\u003e\r\n\u003cbr\u003e\u003chr\u003e\u003ch3\u003eDrivers Licenses\u003c/h3\u003e\u003cimg src=\"products/cat/300/image.jpg\" class=floatimg style=\"float:left\" alt=\"\"\u003e\u003cbr\u003e\u003cbr\u003e\u003cbr\u003e\u003cbr\u003e\u003cbr\u003e\u003cbr\u003e\u003cbr\u003e\u003cbr\u003e\u003cbr\u003e\u003cbr\u003e\u003cbr\u003e\u003cbr\u003e\u003cbr\u003e\u003cbr\u003e\u003cbr\u003e\u003cbr\u003e\u003cbr\u003e\u003cbr\u003e\u003cbr\u003e\u003cbr\u003e\u003ctable class=\"table1\"\u003e\r\n\u003cthead\u003e\r\n\u003ctr\u003e\r\n\u003cth\u003eProduct\u003c/th\u003e\u003cth\u003ePrice\u003c/th\u003e\u003cth\u003eQuantity\u003c/th\u003e\r\n\u003c/tr\u003e\r\n\u003c/thead\u003e\r\n\u003ctbody\u003e\r\n\u003ctr\u003e\r\n\u003ctd\u003eNorway Drivers License\u003c/td\u003e\u003ctd\u003e1150 EUR = 1.891 \u0026#3647;\u003c/td\u003e\u003ctd\u003e\r\n\u003cform name=\"cart\" method=\"post\" action=\"cart.php\"\u003e\r\n\u003cinput value=\"300\" type=\"hidden\" name=\"id\"\u003e\r\n\u003cinput value=\"add\" type=\"hidden\" name=\"action\"\u003e\r\n\u003cinput value=\"1\" type=\"text\" class=\"txt\" name=\"menge\" size=\"2\"\u003e X \u003cinput type=\"submit\" class=\"buttn\" value=\"Buy now\"\u003e\u003c/form\u003e\u003c/td\u003e\r\n\u003c/tr\u003e\r\n\u003ctr\u003e\r\n\u003ctd\u003eDenmark Drivers License\u003c/td\u003e\u003ctd\u003e1150 EUR = 1.891 \u0026#3647;\u003c/td\u003e\u003ctd\u003e\r\n\u003cform name=\"cart\" method=\"post\" action=\"cart.php\"\u003e\r\n\u003cinput value=\"301\" type=\"hidden\" name=\"id\"\u003e\r\n\u003cinput value=\"add\" type=\"hidden\" name=\"action\"\u003e\r\n\u003cinput value=\"1\" type=\"text\" class=\"txt\" name=\"menge\" size=\"2\"\u003e X \u003cinput type=\"submit\" class=\"buttn\" value=\"Buy now\"\u003e\u003c/form\u003e\u003c/td\u003e\r\n\u003c/tr\u003e\r\n\u003ctr\u003e\r\n\u003ctd\u003eNetherlands Drivers License\u003c/td\u003e\u003ctd\u003e1150 EUR = 1.891 \u0026#3647;\u003c/td\u003e\u003ctd\u003e\r\n\u003cform name=\"cart\" method=\"post\" action=\"cart.php\"\u003e\r\n\u003cinput value=\"302\" type=\"hidden\" name=\"id\"\u003e\r\n\u003cinput value=\"add\" type=\"hidden\" name=\"action\"\u003e\r\n\u003cinput value=\"1\" type=\"text\" class=\"txt\" name=\"menge\" size=\"2\"\u003e X \u003cinput type=\"submit\" class=\"buttn\" value=\"Buy now\"\u003e\u003c/form\u003e\u003c/td\u003e\r\n\u003c/tr\u003e\r\n\u003ctr\u003e\r\n\u003ctd\u003eUK Drivers License\u003c/td\u003e\u003ctd\u003e1000 EUR = 1.644 \u0026#3647;\u003c/td\u003e\u003ctd\u003e\r\n\u003cform name=\"cart\" method=\"post\" action=\"cart.php\"\u003e\r\n\u003cinput value=\"303\" type=\"hidden\" name=\"id\"\u003e\r\n\u003cinput value=\"add\" type=\"hidden\" name=\"action\"\u003e\r\n\u003cinput value=\"1\" type=\"text\" class=\"txt\" name=\"menge\" size=\"2\"\u003e X \u003cinput type=\"submit\" class=\"buttn\" value=\"Buy now\"\u003e\u003c/form\u003e\u003c/td\u003e\r\n\u003c/tr\u003e\r\n\u003c/tbody\u003e\r\n\u003c/table\u003e\r\n\u003cbr\u003e\r\n\r\n\r\n\r\n\u003cbr\u003e\r\n\u003cdiv class=\"footer\"\u003eabbujjh5vqtq77wg.onion\u003c/div\u003e\r\n\u003c/div\u003e\r\n\u003c/body\u003e\r\n\u003c/html\u003e","pageTitle":"Onion Identity Services - Get your fake passport and a new identity today","responseHeaders":{"CACHE-CONTROL":"no-store, no-cache, must-revalidate, post-check=0, pre-check=0","CONTENT-TYPE":"text/html","DATE":"Tue, 26 Jul 2016 23:06:51 GMT","EXPIRES":"Thu, 19 Nov 1981 08:52:00 GMT","PRAGMA":"no-cache","SERVER":"Apache","SET-COOKIE":"PHPSESSID=r804patleavkndcv1s4p1stdt0; expires=Wed, 27-Jul-2016 03:06:52 GMT; path=/"},"bitcoinAddresses":null,"sshKey":"","ftpFingerprint":"","ftpBanner":"","smtpFingerprint":"","smtpBanner":""}
