{"hiddenService":"apbv6itrkcr7k3ny.onion","webDetected":true,"sshDetected":true,"ricochetDetected":false,"ircDetected":false,"ftpDetected":false,"smtpDetected":false,"bitcoinDetected":false,"mongodbDetected":false,"vncDetected":false,"xmppDetected":false,"serverPoweredBy":"","serverVersion":"Apache","foundApacheModStatus":false,"relatedOnionServices":null,"relatedOnionDomains":null,"linkedSites":["yzqk4qzlzb7cmwvi.onion","5yhkcnlhhtlztb5t.onion","n7a5rsk7ktf4xc5s.onion","eolowe7qae5qmbmt.onion","antifa.torpress2sarn7xw.onion","sociala2zz7ys2ji.onion","und2jtx35butozdh.onion","5rmsvktrpt7zihpm.onion","6i3athikp6hsre2m.onion","zilionku2adniig6.onion","hydraf53r77hxxft.onion","notoriedadefeminista.torpress2sarn7xw.onion","jgyujfb2olkozxgp.onion","67g7jo2sxvkqej2w.onion","jrz524vll72f4ljr.onion","2x6rzvgatbcev7cy.onion","antiscambrasil.torpress2sarn7xw.onion","v4gn2k725iokfu4u.onion","n3jgmvdgzqk7kfgk.onion","zeroerfjaacldxzf.onion","qzbkwswfv5k2oj5d.onion","ocu3errhpxppmwpr.onion","deepdot35wvmeyd5.onion","mpf3i4k43xc2usxj.onion","bmagtqqinsaafwx6.onion","5bfjlqlvnnx422vd.onion","kobrabd77ppgjd2r.onion","lucy.torpress2sarn7xw.onion","hss3uro2hsxfogfq.onion","pirate6hzvsfpuxg.onion","skunksworkedp2cg.onion","er34q2ds7jfc67q5.onion","ver7ij7pqg6onion.onion","visitorfi5kl7q7i.onion","gjobqjj7wyczbqie.onion","anon4jmy3f3ozlv6.onion","tt3j2x4k5ycaa5zt.onion","underdj5ziov3ic7.onion","kpvz7ki2lzvnwve7.onion","7cbqhjnlkivmigxf.onion","fhostingesps6bly.onion","torpress2sarn7xw.onion","popfilesxuru7lsr.onion","obscuredtzevzthp.onion","freedomsct2bsqtn.onion","g52possau3hapcn6.onion","7qsdbetuja5wrdmr.onion","6zc6sejeho3fwrd4.onion","sigaintevyh2rzvw.onion","mail2tor2zyjdctd.onion","torbox3uiot6wchz.onion","uphnm2dgilz4dysl.onion","w363zoq3ylux5rf5.onion","rf3xojfkckdumtvj.onion","redditor3a2spgd6.onion","doxbin5vadxhatzg.onion","piratexx3kbieklb.onion","cloudninetve7kme.onion","4nxnu47qd2spvyv2.onion","goatsecak32amhqm.onion","jjfcjwxf3szomuas.onion","libraryxobbrbj33.onion","wyrgx7vaq7rj4tbp.onion","y5fmhyqdr6r7ddws.onion","pyl7a4ccwgpxm6rd.onion","222222222c7r2gdj.onion","niggervteelq47id.onion","cleversfsg2ctqk4.onion","mymji3a2duev7jp2.onion","zrhpayzdlqrhnfgd.onion","confessx3gx46lwg.onion","chattorci7bcgygp.onion","32qms7q5widd7wke.onion","chat7zlxojqcf3nv.onion","xfmro77i3lixucja.onion","akmb7t5w56jcfgwf.onion","ahhldsqhacklabfw.onion","fb2lib3argrtulnw.onion","kpynyvym6xqi7wz2.onion","iww2iqhwxmnbh4qs.onion","papersqqyihp5b6u.onion","lu4qfnnkbnduxurt.onion","ashleymwbwtbwxee.onion","7kuslhhtlooylgu4.onion","sitesbr4zb63apyb.onion","theches3nacocgsc.onion","wk3ini5gexnpkwm3.onion","tune4xs6mj2evcr6.onion","663wbgqczxp445am.onion","torflix5djtgsbn3.onion","uj3wazyk5u4hnvtk.onion","iqyyzgb6t3bvc6vx.onion","fonts.googleapis.com","www.gifmania.co.uk"],"internalPages":[""],"ipAddresses":null,"openDirectories":null,"exifImages":null,"interestingFiles":null,"pageReferencedDirectories":null,"pgpKeys":null,"hashes":["b3d236fcdd5c3c8dc67fec033eda268b329c620c"],"snapshot":"\u003c!DOCTYPE html\u003e\r\n\u003chtml lang=\"en\"\u003e\r\n\u003chead\u003e\r\n  \u003cmeta charset=\"utf-8\"\u003e\r\n  \u003cmeta http-equiv=\"X-UA-Compatible\" content=\"IE=edge,chrome=1\" /\u003e\r\n\r\n  \u003ctitle\u003eL1NK5 BR\u003c/title\u003e\r\n\r\n  \u003clink rel=\"stylesheet\" href=\"style.css\"\u003e\r\n  \u003clink href=\"http://fonts.googleapis.com/css?family=Monda:400,700\" rel=\"stylesheet\" type=\"text/css\"\u003e\r\n\r\n\u003c/head\u003e\r\n\u003cbody\u003e\r\n\r\n  \u003cheader\u003e\r\n    \u003cp\u003eL1NK5 BR\u003c/font\u003e\u003c/p\u003e\r\n    \u003cp\u003e\u003ca href=\"http://yzqk4qzlzb7cmwvi.onion/\"\u003eL1NKS BR Antigo\u003c/a\u003e.\u003c/p\u003e\r\n  \u003c/header\u003e\r\n\r\n  \u003cmain\u003e\r\n\r\n    \u003cnav\u003e\r\n      \u003cul\u003e\r\n        \u003cli\u003e\u003ca href=\"#Links\"\u003eLinks Br\u003c/a\u003e\u003c/li\u003e\r\n        \u003cli\u003e\u003ca href=\"#fóruns\"\u003eFóruns\u003c/a\u003e\u003c/li\u003e\r\n        \u003cli\u003e\u003ca href=\"#buying\"\u003eBlogs\u003c/a\u003e\u003c/li\u003e\r\n        \u003cli\u003e\u003ca href=\"#getting-started\"\u003ePonto de Partida\u003c/a\u003e\u003c/li\u003e\r\n        \u003cli\u003e\u003ca href=\"#making\"\u003eFerramentas uteis\u003c/a\u003e\u003c/li\u003e\r\n        \u003cli\u003e\u003ca href=\"#sumobot-jr\"\u003eBuscadores\u003c/a\u003e\u003c/li\u003e\r\n        \u003cli\u003e\u003ca href=\"#simplebot\"\u003eDiretórios\u003c/a\u003e\u003c/li\u003e\r\n        \u003cli\u003e\u003ca href=\"#more-bots\"\u003eWeb Host\u003c/a\u003e\u003c/li\u003e\r\n        \u003cli\u003e\u003ca href=\"#halloween\"\u003eImage Host\u003c/a\u003e\u003c/li\u003e\r\n        \u003cli\u003e\u003ca href=\"#christmas\"\u003eFile Host\u003c/a\u003e\u003c/li\u003e\r\n        \u003cli\u003e\u003ca href=\"#home\"\u003eEmails\u003c/a\u003e\u003c/li\u003e\r\n        \u003cli\u003e\u003ca href=\"#office\"\u003eRedes Sociais\u003c/a\u003e\u003c/li\u003e\r\n        \u003cli\u003e\u003ca href=\"#potent-potables\"\u003eMercados\u003c/a\u003e\u003c/li\u003e\r\n        \u003cli\u003e\u003ca href=\"#johnny-five-builds\"\u003ePastebins\u003c/a\u003e\u003c/li\u003e\r\n        \u003cli\u003e\u003ca href=\"#more\"\u003eAtivismo\u003c/a\u003e\u003c/li\u003e\r\n        \u003cli\u003e\u003ca href=\"#inspirational\"\u003eReligião e outras lendas\u003c/a\u003e\u003c/li\u003e\r\n        \u003cli\u003e\u003ca href=\"#build-collections\"\u003eChats\u003c/a\u003e\u003c/li\u003e\r\n        \u003cli\u003e\u003ca href=\"#books\"\u003eLivros\u003c/a\u003e\u003c/li\u003e\r\n        \u003cli\u003e\u003ca href=\"#soldering\"\u003eHacking\u003c/a\u003e\u003c/li\u003e\r\n        \u003cli\u003e\u003ca href=\"#apis\"\u003eSites Parceiros\u003c/a\u003e\u003c/li\u003e\r\n        \u003cli\u003e\u003ca href=\"#wireless\"\u003eScam\u003c/a\u003e\u003c/li\u003e\r\n        \u003cli\u003e\u003ca href=\"#other\"\u003eOutros\u003c/a\u003e\u003c/li\u003e\r\n      \u003c/ul\u003e\r\n    \u003c/nav\u003e\r\n\r\n    \u003cdiv class=\"flex-wrapper\"\u003e\r\n\r\n    \u003ch1\u003eL1NK5 BR\u003c/h1\u003e\r\n\r\n    \u003cp\u003eSe quer adicionar seu link envie email para eolo@riseup.net: \u003ca href=\"http://5yhkcnlhhtlztb5t.onion\"\u003e\u003c/p\u003e\u003cbr\u003e\r\n\u003cmarquee\u003e\r\n\u003cimg src=\"http://www.gifmania.co.uk/Web-Design-Animated-Gifs/Animated-Symbols/Anarchists-Symbols/Black-Anarchy-Flag-90834.gif\" width=\"120\" height=\"82\" alt=\"Draac Ape\"\u003e\r\n\u003c/marquee\u003e\r\n\r\n\u003cbr\u003e\r\n\r\n\u003cmarquee direction=\"right\"\u003e\u003cB\u003eNão sou ovelha para ter pastor ,nem escravo para ter Senhor!\u003cb\u003e\u003c/marquee\u003e \r\n\r\n    \u003ch2 id=\"installs\"\u003eLinks BR\u003c/h2\u003e\r\n    \u003cp class=\"note\"\u003e\u003cstrong\u003eNOTA:\u003c/strong\u003e: Lista de sites Brasileiros na darknet\r\nOs usuarios merecem um local com todos os sites para poder conferir e decidir quais se adequam a seu gosto pessoal.\r\n\r\n    Cuidado com golpes e mentiras , não espalhem boatos , pesquisem antes de acreditar em coisas da deep.\u003c/p\u003e\u003cbr\u003e\r\n  \u003cul\u003e\r\n\u003cli\u003eNovo Palmares 2.0\u003ca href=\"http://n7a5rsk7ktf4xc5s.onion/\" target=\"_blank\" \u003ePalmares A prova de fakes\u003c/a\u003e)\u003c/li\u003e\r\n\u003cli\u003ePalmares Site\u003ca href=\"http://eolowe7qae5qmbmt.onion/\" target=\"_blank\" \u003ePalmares Site\u003c/a\u003e)\u003c/li\u003e\r\n\u003cli\u003eMobiliza Ação\u003ca href=\"http://antifa.torpress2sarn7xw.onion/\" target=\"_blank\" \u003eMobiliza Ação\u003c/a\u003e)\u003c/li\u003e\r\n\u003cli\u003eChat BR\u003ca href=\"http://sociala2zz7ys2ji.onion/\" target=\"_blank\" \u003eChat BR\u003c/a\u003e)\u003c/li\u003e\r\n\u003cli\u003eSarava\u003ca href=\"http://und2jtx35butozdh.onion/\" target=\"_blank\" \u003eSarava\u003c/a\u003e)\u003c/li\u003e\r\n\u003cli\u003eOcultismo \u003ca href=\"http://5rmsvktrpt7zihpm.onion/\" target=\"_blank\" \u003eOcultismo \u003c/a\u003e)\u003c/li\u003e\r\n\u003cli\u003eClube dos Mercadores\u003ca href=\"http://6i3athikp6hsre2m.onion/\" target=\"_blank\" \u003eClube dos Mercadores\u003c/a\u003e)\u003c/li\u003e\r\n\u003cli\u003eZilion 2.0\u003ca href=\"http://zilionku2adniig6.onion/\" target=\"_blank\" \u003eZilion 2.0 \u003c/a\u003e)\u003c/li\u003e\r\n\u003cli\u003eHydra Liberdade\u003ca href=\"http://hydraf53r77hxxft.onion/\" target=\"_blank\" \u003eHydra Liberdade\u003c/a\u003e)\u003c/li\u003e\r\n\u003cli\u003eNotoriedade\u003ca href=\"http://notoriedadefeminista.torpress2sarn7xw.onion/\" target=\"_blank\" \u003eNotoriedade Feminista\u003c/a\u003e)\u003c/li\u003e\r\n\u003cli\u003eStreisand\u003ca href=\"http://jgyujfb2olkozxgp.onion/indexbr.html\" target=\"_blank\" \u003eStreisand\u003c/a\u003e)\u003c/li\u003e\r\n\u003cli\u003eCyberia 2.0 Cafe \u0026 club\u003ca href=\"http://67g7jo2sxvkqej2w.onion/\" target=\"_blank\" \u003eCyberia 2.0 \u003c/a\u003e)\u003c/li\u003e\r\n\u003cli\u003ePassa palavra\u003ca href=\"http://jrz524vll72f4ljr.onion/\" target=\"_blank\" \u003ePassa Palavra \u003c/a\u003e)\u003c/li\u003e\r\n\u003cli\u003eSegurança\u003ca href=\"http://2x6rzvgatbcev7cy.onion/\" target=\"_blank\" \u003eSegurança\u003c/a\u003e)\u003c/li\u003e\r\n\u003cli\u003eAnti Scam Brasil\u003ca href=\"http://antiscambrasil.torpress2sarn7xw.onion/\" target=\"_blank\" \u003eAnti Scam Brasil\u003c/a\u003e)\u003c/li\u003e\r\n\u003cli\u003eHidden Answers pt\u003ca href=\"http://v4gn2k725iokfu4u.onion/\" target=\"_blank\" \u003eHidden Answers pt\u003c/a\u003e)\u003c/li\u003e\r\n\u003cli\u003eDark Soul\u003ca href=\"http://n3jgmvdgzqk7kfgk.onion/\" target=\"_blank\" \u003eDark Soul\u003c/a\u003e)\u003c/li\u003e    \r\n\r\n\u003c/ul\u003e\r\n\r\n    \u003ch2 id=\"Forum\"\u003eFóruns\u003c/h2\u003e\r\n    \u003cul\u003e\r\n      \u003cul\u003e\r\n\u003cli\u003eNovo Palmares 2.0\u003ca href=\"http://n7a5rsk7ktf4xc5s.onion/\" target=\"_blank\" \u003ePalmares A prova de fakes\u003c/a\u003e)\u003c/li\u003e\r\n\u003cli\u003eClube dos Mercadores\u003ca href=\"http://6i3athikp6hsre2m.onion/\" target=\"_blank\" \u003eClube dos Mercadores\u003c/a\u003e)\u003c/li\u003e\r\n\u003cli\u003eHydra Liberdade\u003ca href=\"http://hydraf53r77hxxft.onion/\" target=\"_blank\" \u003eHydra Liberdade\u003c/a\u003e)\u003c/li\u003e\r\n\u003cli\u003eCyberia 2.0 Cafe \u0026 club\u003ca href=\"http://67g7jo2sxvkqej2w.onion/\" target=\"_blank\" \u003eCyberia 2.0 \u003c/a\u003e)\u003c/li\u003e\r\n\u003cli\u003eGround Zero\u003ca href=\"http://zeroerfjaacldxzf.onion/\" target=\"_blank\" \u003eGround Zero\u003c/a\u003e)\u003c/li\u003e\r\n\u003cli\u003eDay Fórum\u003ca href=\"http://qzbkwswfv5k2oj5d.onion/\" target=\"_blank\" \u003e)day Fórum\u003c/a\u003e)\u003c/li\u003e\r\n\u003cli\u003eAnon GTS\u003ca href=\"http://ocu3errhpxppmwpr.onion/\" target=\"_blank\" \u003e)Anon GTS\u003c/a\u003e)\u003c/li\u003e\r\n\u003cli\u003eDark Soul Fórum\u003ca href=\"http://n3jgmvdgzqk7kfgk.onion/#\" target=\"_blank\" \u003e)Dark Soul\u003c/a\u003e)\u003c/li\u003e\r\n        \u003c/ul\u003e\r\n     \r\n      \r\n    \u003c/ul\u003e\r\n\r\n    \u003ch2 id=\"buying\"\u003eBLogs\u003c/h2\u003e\r\n   \u003cul\u003e\r\n\u003cli\u003eNovo Palmares 2.0\u003ca href=\"http://n7a5rsk7ktf4xc5s.onion/\" target=\"_blank\" \u003ePalmares A prova de fakes\u003c/a\u003e)\u003c/li\u003e\r\n\u003cli\u003ePalmares Site\u003ca href=\"http://eolowe7qae5qmbmt.onion/\" target=\"_blank\" \u003ePalmares Site\u003c/a\u003e)\u003c/li\u003e\r\n\u003cli\u003eMobiliza Ação\u003ca href=\"http://antifa.torpress2sarn7xw.onion/\" target=\"_blank\" \u003eMobiliza Ação\u003c/a\u003e)\u003c/li\u003e\r\n\u003cli\u003eOcultismo \u003ca href=\"http://5rmsvktrpt7zihpm.onion/\" target=\"_blank\" \u003eOcultismo \u003c/a\u003e)\u003c/li\u003e\r\n\u003cli\u003eZilion 2.0\u003ca href=\"http://zilionku2adniig6.onion/\" target=\"_blank\" \u003eZilion 2.0 \u003c/a\u003e)\u003c/li\u003e\r\n\u003cli\u003eNotoriedade\u003ca href=\"http://notoriedadefeminista.torpress2sarn7xw.onion/\" target=\"_blank\" \u003eNotoriedade Feminista\u003c/a\u003e)\u003c/li\u003e\r\n\u003cli\u003eStreisand\u003ca href=\"http://jgyujfb2olkozxgp.onion/indexbr.html\" target=\"_blank\" \u003eStreisand\u003c/a\u003e)\u003c/li\u003e\r\n\u003cli\u003ePassa palavra\u003ca href=\"http://jrz524vll72f4ljr.onion/\" target=\"_blank\" \u003ePassa Palavra \u003c/a\u003e)\u003c/li\u003e\r\n\u003cli\u003eSegurança\u003ca href=\"http://2x6rzvgatbcev7cy.onion/\" target=\"_blank\" \u003eSegurança\u003c/a\u003e)\u003c/li\u003e\r\n\u003cli\u003eAnti Scam Brasil\u003ca href=\"http://antiscambrasil.torpress2sarn7xw.onion/\" target=\"_blank\" \u003eAnti Scam Brasil\u003c/a\u003e)\u003c/li\u003e\r\n\u003cli\u003eDeep Dot Web\u003ca href=\"http://deepdot35wvmeyd5.onion/\" target=\"_blank\" \u003eDeep Dot Web\u003c/a\u003e)\u003c/li\u003e\r\n\u003cli\u003eSamWhited\u003ca href=\"http://mpf3i4k43xc2usxj.onion/\" target=\"_blank\" \u003eSamWhited\u003c/a\u003e)\u003c/li\u003e\r\n\u003cli\u003eCanal do Vanderson O Nerd\u003ca href=\"http://bmagtqqinsaafwx6.onion/\" target=\"_blank\" \u003eCanal do vanderson O Nerd\u003c/a\u003e)\u003c/li\u003e\r\n\u003cli\u003eMexApi\u003ca href=\"http://5bfjlqlvnnx422vd.onion/\" target=\"_blank\" \u003eMexApi\u003c/a\u003e)\u003c/li\u003e\r\n\u003cli\u003eScott Arciszewski\u003ca href=\"http://kobrabd77ppgjd2r.onion/\" target=\"_blank\" \u003eScott Arciszewski\u003c/a\u003e)\u003c/li\u003e\r\n\u003cli\u003eLucy\u003ca href=\"http://lucy.torpress2sarn7xw.onion/\" target=\"_blank\" \u003eLucy\u003c/a\u003e)\u003c/li\u003e\r\n\r\n\r\n  \u003ch2 id=\"getting-started\"\u003ePonto de Partida\u003c/h2\u003e\r\n    \u003cul\u003e\r\n\r\n\r\n\u003cli\u003eBuscador\u003ca href=\"http://hss3uro2hsxfogfq.onion/\" target=\"_blank\" \u003eNot Evil\u003c/a\u003e)\u003c/li\u003e\r\n\u003cli\u003eChat BR\u003ca href=\"http://sociala2zz7ys2ji.onion/\" target=\"_blank\" \u003eChat BR\u003c/a\u003e)\u003c/li\u003e\r\n\u003cli\u003eAnti Scam Brasil\u003ca href=\"http://antiscambrasil.torpress2sarn7xw.onion/\" target=\"_blank\" \u003eAnti Scam Brasil\u003c/a\u003e)\u003c/li\u003e\r\n\u003cli\u003eHidden Answers pt\u003ca href=\"http://v4gn2k725iokfu4u.onion/\" target=\"_blank\" \u003eHidden Answers pt\u003c/a\u003e)\u003c/li\r\n\u003cli\u003ePirate Social\u003ca href=\"http://pirate6hzvsfpuxg.onion/\" target=\"_blank\" \u003ePirate Social\u003c/a\u003e)\u003c/li\u003e\r\n\u003cli\u003eHary71\u003ca href=\"http://skunksworkedp2cg.onion/\" target=\"_blank\" \u003eHary71\u003c/a\u003e)\u003c/li\u003e\r\n \r\n\r\n\r\n\r\n \u003ch2 id=\"making\"\u003eFerramentas\u003c/h2\u003e\r\n    \u003cul\u003e\r\n\r\n\r\n\r\n\u003cli\u003eXSS Http Injector\u003ca href=\"http://er34q2ds7jfc67q5.onion/\" target=\"_blank\" \u003eXss Injector\u003c/a\u003e)\u003c/li\u003e\r\n\u003cli\u003ecebolinha\u003ca href=\"http://ver7ij7pqg6onion.onion/chaveonion/\" target=\"_blank\" \u003ecebolinha\u003c/a\u003e)\u003c/li\u003e\r\n    \r\n\r\n\u003c/ul\u003e\r\n\r\n    \u003ch2 id=\"sumobot-jr\"\u003eBuscadores\u003c/h2\u003e\r\n    \u003cul\u003e\r\n    \r\n\r\n\u003cli\u003eNot Evil\u003ca href=\"http://hss3uro2hsxfogfq.onion/\" target=\"_blank\" \u003eNot Evil\u003c/a\u003e)\u003c/li\u003e\r\n\u003cli\u003eVisitor\u003ca href=\"http://visitorfi5kl7q7i.onion\" target=\"_blank\" \u003eVisitor\u003c/a\u003e)\u003c/li\u003e\r\n\u003cli\u003eCandle\u003ca href=\"http://gjobqjj7wyczbqie.onion/\" target=\"_blank\" \u003eCandle\u003c/a\u003e)\u003c/li\u003e\r\n\u003cli\u003eTor Search\u003ca href=\"http://anon4jmy3f3ozlv6.onion/\" target=\"_blank\" \u003eTor Search\u003c/a\u003e)\u003c/li\u003e\r\n\r\n\u003c/ul\u003e\r\n\r\n    \u003ch2 id=\"simplebot\"\u003eDiretórios\u003c/h2\u003e\r\n    \u003cul\u003e\r\n\r\n\r\n\u003cli\u003eVisitor\u003ca href=\"http://visitorfi5kl7q7i.onion/links/\" target=\"_blank\" \u003eVisitor\u003c/a\u003e)\u003c/li\u003e\r\n\u003cli\u003eDaniels Web\u003ca href=\"http://tt3j2x4k5ycaa5zt.onion/\" target=\"_blank\" \u003eDaniels Web\u003c/a\u003e)\u003c/li\u003e\r\n\u003cli\u003eUnder Dir\u003ca href=\"http://underdj5ziov3ic7.onion/\" target=\"_blank\" \u003eUnder Dir\u003c/a\u003e)\u003c/li\u003e\r\n\u003cli\u003eThe Hidden Wiki\u003ca href=\"http://kpvz7ki2lzvnwve7.onion/\" target=\"_blank\" \u003eThe Hidden Wiki\u003c/a\u003e)\u003c/li\u003e\r\n\u003cli\u003eThe Onion Crate\u003ca href=\"http://7cbqhjnlkivmigxf.onion/\" target=\"_blank\" \u003eThe Onion Crate\u003c/a\u003e)\u003c/li\u003e   \r\n\r\n\r\n \u003c/ul\u003e\r\n\r\n    \u003ch2 id=\"more-bots\"\u003eWeb Host\u003c/h2\u003e\r\n    \u003cul\u003e\r\n\r\n\r\n\u003cli\u003eFreedom Hosting II\u003ca href=\"http://fhostingesps6bly.onion/\" target=\"_blank\" \u003eFreedom Hosting II\u003c/a\u003e)\u003c/li\u003e\r\n\u003cli\u003eTorPress\u003ca href=\"http://torpress2sarn7xw.onion/\" target=\"_blank\" \u003eTorPress\u003c/a\u003e)\u003c/li\u003e   \r\n    \u003c/ul\u003e\r\n\r\n    \u003ch2 id=\"halloween\"\u003eImage Host\u003c/h2\u003e\r\n    \u003cul\u003e\r\n\r\n\r\n\u003cli\u003ePop Files\u003ca href=\"http://popfilesxuru7lsr.onion/\" target=\"_blank\" \u003ePop Files\u003c/a\u003e)\u003c/li\u003e\r\n\u003cli\u003eObscure Files\u003ca href=\"http://obscuredtzevzthp.onion/\" target=\"_blank\" \u003eObscure Files\u003c/a\u003e)\u003c/li\u003e   \r\n\u003cli\u003ePop Files\u003ca href=\"http://popfilesxuru7lsr.onion/\" target=\"_blank\" \u003ePop Files\u003c/a\u003e)\u003c/li\u003e\r\n\u003cli\u003eFreedom Image Host\u003ca href=\"http://freedomsct2bsqtn.onion/\" target=\"_blank\" \u003eFreedom Image Host\u003c/a\u003e)\u003c/li\u003e\r\n\r\n\u003c/ul\u003e\r\n\r\n    \u003ch2 id=\"christmas\"\u003eFile Host\u003c/h2\u003e\r\n    \u003cul\u003e\r\n     \r\n\r\n\u003cli\u003eModern Upload\u003ca href=\"http://g52possau3hapcn6.onion/\" target=\"_blank\" \u003eModern Upload\u003c/a\u003e)\u003c/li\u003e\r\n\u003cli\u003eObscure Files\u003ca href=\"http://obscuredtzevzthp.onion/\" target=\"_blank\" \u003eObscure Files\u003c/a\u003e)\u003c/li\u003e   \r\n\u003cli\u003eUpload\u003ca href=\"http://7qsdbetuja5wrdmr.onion/\" target=\"_blank\" \u003eUpload\u003c/a\u003e)\u003c/li\u003e\r\n\u003cli\u003eShare Riseup\u003ca href=\"http://6zc6sejeho3fwrd4.onion/\" target=\"_blank\" \u003eShare Riseup\u003c/a\u003e)\u003c/li\u003e\r\n\r\n\r\n    \u003c/ul\u003e\r\n\r\n    \u003ch2 id=\"home\"\u003eEmails\u003c/h2\u003e\r\n    \u003cul\u003e\r\n\r\n\r\n\u003cli\u003eSigaint\u003ca href=\"http://sigaintevyh2rzvw.onion/\" target=\"_blank\" \u003eSigaint\u003c/a\u003e)\u003c/li\u003e\r\n\u003cli\u003eMail2Tor\u003ca href=\"http://mail2tor2zyjdctd.onion/\" target=\"_blank\" \u003eMail2Tor\u003c/a\u003e)\u003c/li\u003e   \r\n\u003cli\u003eTorbox\u003ca href=\"http://torbox3uiot6wchz.onion/\" target=\"_blank\" \u003eTorbox\u003c/a\u003e)\u003c/li\u003e\r\n\u003cli\u003ePGP Mail\u003ca href=\"http://uphnm2dgilz4dysl.onion/\" target=\"_blank\" \u003ePGP Mail\u003c/a\u003e)\u003c/li\u003e\r\n\r\n\r\n\r\n    \u003c/ul\u003e\r\n\r\n    \u003ch2 id=\"office\"\u003eRedes Sociais\u003c/h2\u003e\r\n    \u003cul\u003e\r\n\r\n\u003cli\u003ePirate Social\u003ca href=\"http://pirate6hzvsfpuxg.onion/\" target=\"_blank\" \u003ePirate Social\u003c/a\u003e)\u003c/li\u003e\r\n\u003cli\u003eGalaxy2\u003ca href=\"http://w363zoq3ylux5rf5.onion/\" target=\"_blank\" \u003eGalaxy2\u003c/a\u003e)\u003c/li\u003e   \r\n\u003cli\u003eTorbird\u003ca href=\"http://rf3xojfkckdumtvj.onion/\" target=\"_blank\" \u003eTorbird\u003c/a\u003e)\u003c/li\u003e\r\n\u003cli\u003eReddit\u003ca href=\"http://redditor3a2spgd6.onion/\" target=\"_blank\" \u003eReddit\u003c/a\u003e)\u003c/li\u003e\r\n\u003cli\u003eDark Soul Brasil\u003ca href=\"http://n3jgmvdgzqk7kfgk.onion/darksocial/\" target=\"_blank\" \u003eDark Soul Brasil\u003c/a\u003e)\u003c/li\u003e\r\n    \u003c/ul\u003e\r\n\r\n    \u003ch2 id=\"potent-potables\"\u003eMercados\u003c/h2\u003e\r\n    \u003cul\u003e\r\n\r\n\u003cli\u003eClube dos mercadores\u003ca href=\"http://6i3athikp6hsre2m.onion/\" target=\"_blank\" \u003eClube dos mercadores\u003c/a\u003e)\u003c/li\u003e\r\n\r\n\r\n    \u003c/ul\u003e\r\n\r\n    \u003ch2 id=\"johnny-five-builds\"\u003ePastebins\u003c/h2\u003e\r\n    \u003cul\u003e\r\n  \r\n\u003cli\u003eDoxbin\u003ca href=\"http://doxbin5vadxhatzg.onion/\" target=\"_blank\" \u003eDoxbin\u003c/a\u003e)\u003c/li\u003e\r\n\u003cli\u003eZerobin\u003ca href=\"http://piratexx3kbieklb.onion/\" target=\"_blank\" \u003eZerobin\u003c/a\u003e)\u003c/li\u003e   \r\n\u003cli\u003eCloudNine\u003ca href=\"http://cloudninetve7kme.onion/\" target=\"_blank\" \u003eCloudnine\u003c/a\u003e)\u003c/li\u003e\r\n\u003cli\u003ePastThis\u003ca href=\"http://4nxnu47qd2spvyv2.onion/\" target=\"_blank\" \u003ePastThis\u003c/a\u003e)\u003c/li\u003e\r\n\u003cli\u003eGoatSec 0bin\u003ca href=\"http://goatsecak32amhqm.onion/\" target=\"_blank\" \u003eGoatSec 0bin\u003c/a\u003e)\u003c/li\u003e\r\n\u003cli\u003ePrvt.Zone\u003ca href=\"http://jjfcjwxf3szomuas.onion/\" target=\"_blank\" \u003ePrvt.Zone\u003c/a\u003e)\u003c/li\u003e\r\n\r\n\r\n    \u003c/ul\u003e\r\n\r\n    \u003ch2 id=\"more\"\u003eAtivismo\u003c/h2\u003e\r\n    \u003cul\u003e\r\n\r\n\r\n  \r\n\u003cli\u003ePalmares 2.0\u003ca href=\"http://n7a5rsk7ktf4xc5s.onion/\" target=\"_blank\" \u003ePalmares 2.0\u003c/a\u003e)\u003c/li\u003e\r\n\u003cli\u003eFreedom Project\u003ca href=\"http://libraryxobbrbj33.onion/\" target=\"_blank\" \u003eFreedom Project\u003c/a\u003e)\u003c/li\u003e   \r\n\u003cli\u003eMach, was wirklich zählt\u003ca href=\"http://wyrgx7vaq7rj4tbp.onion/\" target=\"_blank\" \u003eMach, was wirklich zählt\u003c/a\u003e)\u003c/li\u003e\r\n\u003cli\u003eAnarplex\u003ca href=\"http://y5fmhyqdr6r7ddws.onion/files/lotnv.html\" target=\"_blank\" \u003eAnarplex\u003c/a\u003e)\u003c/li\u003e\r\n\u003cli\u003eCode Green\u003ca href=\"http://pyl7a4ccwgpxm6rd.onion/w/index.php/Main_Page\" target=\"_blank\" \u003eCode Green\u003c/a\u003e)\u003c/li\u003e\r\n\r\n\r\n    \u003c/ul\u003e\r\n\r\n    \u003ch2 id=\"inspirational\"\u003eReligião e outras lendas\u003c/h2\u003e\r\n    \u003cul\u003e\r\n\r\n\r\n\u003cli\u003eFuck Islam\u003ca href=\"http://222222222c7r2gdj.onion/\" target=\"_blank\" \u003eFuck Islam\u003c/a\u003e)\u003c/li\u003e\r\n\u003cli\u003eDança Jesus\u003ca href=\"http://niggervteelq47id.onion/\" target=\"_blank\" \u003eDança Jesus\u003c/a\u003e)\u003c/li\u003e\r\n\u003cli\u003eClever Sincerity\u003ca href=\"http://cleversfsg2ctqk4.onion/\" target=\"_blank\" \u003eClever Sincerity\u003c/a\u003e)\u003c/li\u003e\r\n\u003cli\u003eThe End\u003ca href=\"http://mymji3a2duev7jp2.onion/\" target=\"_blank\" \u003eThe End\u003c/a\u003e)\u003c/li\u003e\r\n\u003cli\u003eChurch of Satoshi Nakamoto\u003ca href=\"http://zrhpayzdlqrhnfgd.onion/\" target=\"_blank\" \u003eChurch of Satoshi Nakamoto\u003c/a\u003e)\u003c/li\u003e\r\n\u003cli\u003eAnonymous Confessions\u003ca href=\"http://confessx3gx46lwg.onion/\" target=\"_blank\" \u003eAnonymous Confessions\u003c/a\u003e)\u003c/li\u003e\r\n\r\n\r\n\r\n    \u003c/ul\u003e\r\n\r\n    \u003ch2 id=\"build-collections\"\u003eChats\u003c/h2\u003e\r\n    \u003cul\u003e\r\n\u003cli\u003eChat BR\u003ca href=\"http://sociala2zz7ys2ji.onion/\" target=\"_blank\" \u003eChat BR\u003c/a\u003e)\u003c/li\u003e\r\n\u003cli\u003eChat Tor\u003ca href=\"http://chattorci7bcgygp.onion/\" target=\"_blank\" \u003eChat Tor\u003c/a\u003e)\u003c/li\u003e\r\n\u003cli\u003eOnion IRC\u003ca href=\"http://32qms7q5widd7wke.onion/\" target=\"_blank\" \u003eOnion IRC\u003c/a\u003e)\u003c/li\u003e\r\n\u003cli\u003eRetro Share\u003ca href=\"http://chat7zlxojqcf3nv.onion/\" target=\"_blank\" \u003eRetro Share\u003c/a\u003e)\u003c/li\u003e\r\n\u003cli\u003eNot Evil Chat\u003ca href=\"http://hss3uro2hsxfogfq.onion/chat/\" target=\"_blank\" \u003eNot Evil Chat\u003c/a\u003e)\u003c/li\u003e\r\n\u003cli\u003eDark Soul Chat\u003ca href=\"http://n3jgmvdgzqk7kfgk.onion/darkchat/login.php\" target=\"_blank\" \u003eDark Soul Chat\u003c/a\u003e)\u003c/li\u003e\r\n\r\n   \u003c/ul\u003e\r\n\r\n    \u003ch2 id=\"books\"\u003eLivros\u003c/h2\u003e\r\n    \u003cul\u003e\r\n\r\n\u003cli\u003eImperial Library\u003ca href=\"http://xfmro77i3lixucja.onion/\" target=\"_blank\" \u003eImperial Library\u003c/a\u003e)\u003c/li\u003e\r\n\u003cli\u003eBiblioteca 1\u003ca href=\"http://akmb7t5w56jcfgwf.onion/books/sorted/\" target=\"_blank\" \u003eBiblioteca 1\u003c/a\u003e)\u003c/li\u003e\r\n\u003cli\u003eBiblioteca 2\u003ca href=\"http://ahhldsqhacklabfw.onion/data/books/\" target=\"_blank\" \u003eBiblioteca 2\u003c/a\u003e)\u003c/li\u003e\r\n\u003cli\u003eBiblioteca Russa\u003ca href=\"http://fb2lib3argrtulnw.onion/\" target=\"_blank\" \u003eBiblioteca Russa\u003c/a\u003e)\u003c/li\u003e\r\n\u003cli\u003eParazite\u003ca href=\"http://kpynyvym6xqi7wz2.onion/\" target=\"_blank\" \u003eParazite\u003c/a\u003e)\u003c/li\u003e\r\n\u003cli\u003eMarx/Engels\u003ca href=\"http://iww2iqhwxmnbh4qs.onion/\" target=\"_blank\" \u003eMarx/Engels\u003c/a\u003e)\u003c/li\u003e\r\n\u003cli\u003eMediaGoblin logo \u003ca href=\"http://papersqqyihp5b6u.onion/\" target=\"_blank\" \u003eMediaGoblin logo \u003c/a\u003e)\u003c/li\u003e\r\n\r\n    \u003c/ul\u003e\r\n\r\n    \u003ch2 id=\"soldering\"\u003eHacking\u003c/h2\u003e\r\n    \r\n    \u003cul\u003e\r\n\r\n\r\n\u003cli\u003eCyber Guerrilha\u003ca href=\"http://lu4qfnnkbnduxurt.onion/\" target=\"_blank\" \u003eBiblioteca 1\u003c/a\u003e)\u003c/li\u003e\r\n\u003cli\u003eAshley Madison Site Dumps\u003ca href=\"http://ashleymwbwtbwxee.onion/\" target=\"_blank\" \u003eAshley Madison Site Dumps\u003c/a\u003e)\u003c/li\u003e\r\n\u003cli\u003eBiblioteca Russa\u003ca href=\"http://fb2lib3argrtulnw.onion/\" target=\"_blank\" \u003eBiblioteca Russa\u003c/a\u003e)\u003c/li\u003e\r\n\u003cli\u003eTools\u003ca href=\"http://7kuslhhtlooylgu4.onion/\" target=\"_blank\" \u003eTools\u003c/a\u003e)\u003c/li\u003e\r\n\r\n    \u003c/ul\u003e\r\n\r\n    \u003ch2 id=\"apis\"\u003eSites Parceiros\u003c/h2\u003e\r\n    \u003cul\u003e\r\n\u003cli\u003ePalmares 2.0\u003ca href=\"http://n7a5rsk7ktf4xc5s.onion/\" target=\"_blank\" \u003ePalmares 2.0\u003c/a\u003e)\u003c/li\u003e\r\n\u003cli\u003eMobiliza Ação\u003ca href=\"http://antifa.torpress2sarn7xw.onion/\" target=\"_blank\" \u003eMobiliza Ação\u003c/a\u003e)\u003c/li\u003e\r\n\u003cli\u003eChat BR\u003ca href=\"http://sociala2zz7ys2ji.onion/\" target=\"_blank\" \u003eChat BR\u003c/a\u003e)\u003c/li\u003e\r\n\u003cli\u003eHydra Lyberdade\u003ca href=\"http://hydraf53r77hxxft.onion/\" target=\"_blank\" \u003eHydra Lyberdade\u003c/a\u003e)\u003c/li\u003e\r\n\u003cli\u003ePirate Social\u003ca href=\"http://pirate6hzvsfpuxg.onion/\" target=\"_blank\" \u003ePirate Social\u003c/a\u003e)\u003c/li\u003e\r\n\u003cli\u003eDark Soul\u003ca href=\"http://n3jgmvdgzqk7kfgk.onion/\" target=\"_blank\" \u003eDark Soul\u003c/a\u003e)\u003c/li\u003e\r\n\r\n    \u003c/ul\u003e\r\n\r\n    \u003ch2 id=\"wireless\"\u003eScam\u003c/h2\u003e\r\n\r\n\r\n    \u003cul\u003e\r\n\r\n\r\n\u003cli\u003eRanking de Sites Brasileiros\u003ca href=\"http://sitesbr4zb63apyb.onion\" target=\"_blank\" \u003eRanking de Sites Brasileiros\u003c/a\u003e)\u003c/li\u003e\r\n\r\n\r\n    \u003c/ul\u003e\r\n\r\n    \u003ch2 id=\"other\"\u003eOther\u003c/h2\u003e\r\n    \u003cul\u003e\r\n\r\n\r\n\r\n\u003cli\u003eThe Chess\u003ca href=\"http://theches3nacocgsc.onion\" target=\"_blank\" \u003eThe Chess\u003c/a\u003e)\u003c/li\u003e\r\n\u003cli\u003eDice Roller\u003ca href=\"http://wk3ini5gexnpkwm3.onion/\" target=\"_blank\" \u003eDice Roller\u003c/a\u003e)\u003c/li\u003e\r\n\u003cli\u003eDeep Tune\u003ca href=\"http://tune4xs6mj2evcr6.onion/\" target=\"_blank\" \u003eDeep Tune\u003c/a\u003e)\u003c/li\u003e\r\n\u003cli\u003eMusic Collection\u003ca href=\"http://663wbgqczxp445am.onion/\" target=\"_blank\" \u003eMusic Collection\u003c/a\u003e)\u003c/li\u003e\r\n\u003cli\u003eTorflix\u003ca href=\"http://torflix5djtgsbn3.onion/\" target=\"_blank\" \u003eTorflix\u003c/a\u003e)\u003c/li\u003e\r\n\u003cli\u003eThe Pirate Bay\u003ca href=\"http://uj3wazyk5u4hnvtk.onion/\" target=\"_blank\" \u003eThe Pirate Bay\u003c/a\u003e)\u003c/li\u003e\r\n\r\n\r\n    \u003c/ul\u003e\r\n\u003cmarquee\u003e\r\n\u003cimg src=\"http://www.gifmania.co.uk/Web-Design-Animated-Gifs/Animated-Symbols/Anarchists-Symbols/Black-Anarchy-Flag-90834.gif\" width=\"120\" height=\"82\" alt=\"Draac Ape\"\u003e\r\n\u003c/marquee\u003e\r\n  \u003c/div\u003e\r\n\r\n  \u003c/main\u003e\r\n\r\n  \u003cfooter\u003e\r\n    \u003cp\u003e\u003ca href=\"http://iqyyzgb6t3bvc6vx.onion/keys/1465828084.txt\"\u003ehttp://iqyyzgb6t3bvc6vx.onion/keys/1468112504.txt\u003c/a\u003e - eolo@riseup.net!\u003c/p\u003e\r\n    \u003cp\u003eProduzido Por: \u003ca rel=\"The Pirates™\" href=\"http://n7a5rsk7ktf4xc5s.onion\"\u003ePalmares 2.0\u003c/a\u003e.\u003c/p\u003e\r\n  \u003c/footer\u003e\r\n\r\n\u003c/body\u003e\r\n\u003c/html\u003e\r\n","pageTitle":"L1NK5 BR","responseHeaders":{"ACCEPT-RANGES":"bytes","CONTENT-TYPE":"text/html","DATE":"Tue, 26 Jul 2016 21:55:32 GMT","ETAG":"\"42f0-5373d9e81734e-gzip\"","LAST-MODIFIED":"Sun, 10 Jul 2016 01:04:35 GMT","SERVER":"Apache","VARY":"Accept-Encoding","X-CONTENT-TYPE-OPTIONS":"nosniff","X-FRAME-OPTIONS":"sameorigin","X-XSS-PROTECTION":"1; mode=block"},"bitcoinAddresses":null,"sshKey":"81:cb:d2:d4:f7:e4:8c:6b:1a:92:07:42:cd:e2:42:23","ftpFingerprint":"","ftpBanner":"","smtpFingerprint":"","smtpBanner":""}
