{"hiddenService":"apchatxshsnyi6s3.onion","webDetected":true,"sshDetected":false,"ricochetDetected":false,"ircDetected":false,"ftpDetected":false,"smtpDetected":false,"bitcoinDetected":false,"mongodbDetected":false,"vncDetected":false,"xmppDetected":false,"serverPoweredBy":"","serverVersion":"Apache","foundApacheModStatus":false,"relatedOnionServices":null,"relatedOnionDomains":null,"linkedSites":["fonts.googleapis.com","daneden.me","github.com"],"internalPages":[""],"ipAddresses":null,"openDirectories":null,"exifImages":null,"interestingFiles":null,"pageReferencedDirectories":["css","css","css","css","css","img","img","/upgrade","/upgrade"],"pgpKeys":null,"hashes":["8ced73811e1909135d877f7fbe1b24a00f267618"],"snapshot":"\u003c!doctype html\u003e\r\n\u003chtml\u003e\r\n\u003chead\u003e\r\n\u003cmeta charset=\"utf-8\"\u003e\r\n\u003cmeta name=\"viewport\" content=\"width=device-width, maximum-scale=1\"\u003e\r\n\r\n\u003ctitle\u003eAppaloosa Chat\u003c/title\u003e\r\n\u003clink rel=\"icon\" href=\"favicon.png\" type=\"image/png\"\u003e\r\n\u003clink rel=\"shortcut icon\" href=\"favicon.ico\" type=\"img/x-icon\"\u003e\r\n\r\n\u003clink href='http://fonts.googleapis.com/css?family=Montserrat:400,700' rel='stylesheet' type='text/css'\u003e\r\n\u003clink href='http://fonts.googleapis.com/css?family=Open+Sans:400,300,800italic,700italic,600italic,400italic,300italic,800,700,600' rel='stylesheet' type='text/css'\u003e\r\n\r\n\u003clink href=\"css/bootstrap.css\" rel=\"stylesheet\" type=\"text/css\"\u003e\r\n\u003clink href=\"css/style.css\" rel=\"stylesheet\" type=\"text/css\"\u003e\r\n\u003clink href=\"css/font-awesome.css\" rel=\"stylesheet\" type=\"text/css\"\u003e\r\n\u003clink href=\"css/responsive.css\" rel=\"stylesheet\" type=\"text/css\"\u003e\r\n\u003clink href=\"css/animate.css\" rel=\"stylesheet\" type=\"text/css\"\u003e\r\n\u003c/head\u003e\r\n\u003cbody\u003e\r\n\u003cdiv style=\"overflow:hidden;\"\u003e\r\n\u003cheader class=\"header\" id=\"top\"\u003e\r\n\t\u003cdiv class=\"container\"\u003e\r\n    \t\u003cfigure class=\"logo animated fadeInDown delay-07s\"\u003e\r\n        \t\u003ca href=\"/\"\u003e\u003cimg src=\"img/logo.png\" alt=\"\"\u003e\u003c/a\u003e\r\n        \u003c/figure\u003e\r\n   \t  \u003ch1 class=\"animated fadeInDown delay-07s\"\u003eAppaloosa Chat\u003c/h1\u003e\r\n   \t  \u003cul class=\"we-create animated fadeInUp delay-1s\"\u003e\r\n    \t  \u003cli\u003eFAST SECURE AND ANONYMOUS DARKNET MESSAGING SERVICE\u003c/li\u003e\r\n  \t  \u003c/ul\u003e\r\n      \r\n      \r\n      \r\n      \r\n      \r\n      \r\n\t\t \u003ca class=\"link1 animated fadeInUp delay-06s\" href=\"?login=true\"\u003eLOG IN\u003c/a\u003e\r\n         \u003cspan\u003e\u0026nbsp;\u0026nbsp;\u0026nbsp;\u0026nbsp;\u0026nbsp;\u003c/span\u003e\r\n     \t \u003ca class=\"link1 animated fadeInUp delay-06s\" href=\"?signup=true\"\u003eSIGN UP\u003c/a\u003e\r\n         \r\n         \r\n\r\n\r\n\r\n\r\n    \u003c/div\u003e\r\n \u003c/header\u003e\r\n\u003c/div\u003e\r\n\u003cnav class=\"main-nav-outer\" id=\"nav-bar\"\u003e\r\n\t\u003cdiv class=\"container\"\u003e\r\n        \u003cul class=\"main-nav\"\u003e\r\n        \t\u003cli\u003e\u003ca href=\"/#about\"\u003eAbout\u003c/a\u003e\u003c/li\u003e\r\n            \u003cli\u003e\u003ca href=\"/#pricing\"\u003ePricing\u003c/a\u003e\u003c/li\u003e\r\n            \u003cli class=\"small-logo\"\u003e\u003ca href=\"/#top\"\u003e\u003cimg src=\"img/small-logo.png\" alt=\"\"\u003e\u003c/a\u003e\u003c/li\u003e\r\n            \u003cli\u003e\u003ca href=\"/?login=true\"\u003eLog in\u003c/a\u003e\u003c/li\u003e\r\n            \u003cli\u003e\u003ca href=\"/?signup=true\"\u003eSign up\u003c/a\u003e\u003c/li\u003e\r\n        \u003c/ul\u003e\r\n    \u003c/div\u003e\r\n\u003c/nav\u003e\r\n\u003csection class=\"footer\"\u003e\u003c/section\u003e\r\n\u003csection class=\"main-section about\" id=\"about\"\u003e\r\n\t\u003cdiv class=\"container\"\u003e\r\n    \t\u003cdiv class=\"row\"\u003e\r\n        \t\u003cdiv class=\"col-lg-7 col-sm-8 featured-work\"\u003e\r\n            \t\u003ch2\u003eAbout Appaloosa Chat\u003c/h2\u003e\r\n            \t\u003cp class=\"padding-b\"\u003eAppaloosa Chat is an highly anonymous system to exchange messages on Tor. When you sign up no information is needed. Your ID is automathically generated and you are ready to go. But first you may want to know something more. So down here you find some FAQ.\u003c/p\u003e\r\n            \t\u003cdiv class=\"featured-box\"\u003e\r\n                \t\u003cdiv class=\"featured-box-col1 animated fadeInRight delay-02s\"\u003e\r\n                    \t\u003ci class=\"fa-inbox\"\u003e\u003c/i\u003e\r\n                    \u003c/div\u003e\t\r\n                \t\u003cdiv class=\"featured-box-col2 animated fadeInRight delay-02s\"\u003e\r\n                        \u003ch3\u003eWho can I send messages to?\u003c/h3\u003e\r\n                        \u003cp\u003eYou can exchange messages only with other Appaloosa Chat users. This is not an email provider so you can't write to people outside this website. This limitation increases anonymity and safety.\u003c/p\u003e\r\n                    \u003c/div\u003e    \r\n                \u003c/div\u003e\r\n                \u003cdiv class=\"featured-box\"\u003e\r\n                \t\u003cdiv class=\"featured-box-col1 animated fadeInRight delay-04s\"\u003e\r\n                    \t\u003ci class=\"fa-eye-slash\"\u003e\u003c/i\u003e\r\n                    \u003c/div\u003e\t\r\n                \t\u003cdiv class=\"featured-box-col2 animated fadeInRight delay-04s\"\u003e\r\n                        \u003ch3\u003eHow can I be sure you won't spy my conversations?\u003c/h3\u003e\r\n                        \u003cp\u003eYou can't. So if you need extra privacy encrypt your messages with your recipient's public key.\u003c/p\u003e\r\n                    \u003c/div\u003e    \r\n                \u003c/div\u003e\r\n                \u003cdiv class=\"featured-box\"\u003e\r\n                \t\u003cdiv class=\"featured-box-col1 animated fadeInRight delay-06s\"\u003e\r\n                    \t\u003ci class=\"fa-exclamation-triangle\"\u003e\u003c/i\u003e\r\n                    \u003c/div\u003e\t\r\n                \t\u003cdiv class=\"featured-box-col2 animated fadeInRight delay-06s\"\u003e\r\n                        \u003ch3\u003eI trust you, but what if someone hacks you?\u003c/h3\u003e\r\n                        \u003cp\u003eWe run a tight ship but again we suggest you to encrypt your messages so you don't have to worry about anything.\u003c/p\u003e\r\n                    \u003c/div\u003e    \r\n                \u003c/div\u003e\r\n                \u003cdiv class=\"featured-box\"\u003e\r\n                \t\u003cdiv class=\"featured-box-col1 animated fadeInRight delay-08s\"\u003e\r\n                    \t\u003ci class=\"fa-shopping-cart\"\u003e\u003c/i\u003e\r\n                    \u003c/div\u003e\t\r\n                \t\u003cdiv class=\"featured-box-col2 animated fadeInRight delay-08s\"\u003e\r\n                        \u003ch3\u003eHow much does it cost?\u003c/h3\u003e\r\n                        \u003cp\u003eRegular accounts are free but have a limitation of 100 messages per year and you can't write to more than 10 different users. Premium accounts cost $29 only once to activate and are limited to 1000 messages per year and 20 contacts. Business accounts cost $89 only once to activate ($60 if you already have a Premium account). Once you go Business you won't have limitations anymore and you'll have access to a bunch of other benefits.\u003c/p\u003e\r\n                \t\u003c/div\u003e    \r\n                \u003c/div\u003e\r\n                \u003cdiv class=\"featured-box\"\u003e\r\n                \t\u003cdiv class=\"featured-box-col1 animated fadeInRight delay-1s\"\u003e\r\n                    \t\u003ci class=\"fa-star\"\u003e\u003c/i\u003e\r\n                    \u003c/div\u003e\t\r\n                \t\u003cdiv class=\"featured-box-col2 animated fadeInRight delay-1s\"\u003e\r\n                        \u003ch3\u003eWhat other benefits does a premium account offer?\u003c/h3\u003e\r\n                        \u003cp\u003eYou can choose an username instead of using the regular numeric ID. You will have to solve less captcha challenges and, if you trust Appaloosa Chat, you can store your recipients public keys and set the messages to automatically encrypt when you send them. Original messages won't be stored.\u003c/p\u003e\r\n                    \u003c/div\u003e    \r\n                \u003c/div\u003e\r\n                \u003cdiv class=\"featured-box\"\u003e\r\n                \t\u003cdiv class=\"featured-box-col1 animated fadeInRight delay-1s\"\u003e\r\n                    \t\u003ci class=\"fa-key\"\u003e\u003c/i\u003e\r\n                    \u003c/div\u003e\t\r\n                \t\u003cdiv class=\"featured-box-col2 animated fadeInRight delay-1s\"\u003e\r\n                        \u003ch3\u003eI lost my password, what can I do?\u003c/h3\u003e\r\n                        \u003cp\u003eThere's no password recovery system so sign up a new account.\u003c/p\u003e\r\n                    \u003c/div\u003e    \r\n                \u003c/div\u003e\r\n                \u003cdiv class=\"featured-box\"\u003e\r\n                \t\u003cdiv class=\"featured-box-col1 animated fadeInRight delay-1s\"\u003e\r\n                    \t\u003ci class=\"fa-refresh\"\u003e\u003c/i\u003e\r\n                    \u003c/div\u003e\t\r\n                \t\u003cdiv class=\"featured-box-col2 animated fadeInRight delay-1s\"\u003e\r\n                        \u003ch3\u003eCan I change my password?\u003c/h3\u003e\r\n                        \u003cp\u003eYes. Click \u003ca style=\"text-decoration:none\" href=\"change_password.php\"\u003ehere\u003c/a\u003e.\u003c/p\u003e\r\n                    \u003c/div\u003e    \r\n                \u003c/div\u003e\r\n                \u003cdiv class=\"featured-box\"\u003e\r\n                \t\u003cdiv class=\"featured-box-col1 animated fadeInRight delay-1s\"\u003e\r\n                    \t\u003ci class=\"fa-spinner\"\u003e\u003c/i\u003e\r\n                    \u003c/div\u003e\t\r\n                \t\u003cdiv class=\"featured-box-col2 animated fadeInRight delay-1s\"\u003e\r\n                        \u003ch3\u003eCan I change my business customized username?\u003c/h3\u003e\r\n                        \u003cp\u003eNo.\u003c/p\u003e\r\n                    \u003c/div\u003e    \r\n                \u003c/div\u003e\r\n            \u003c/div\u003e\r\n        \u003c/div\u003e\r\n\t\u003c/div\u003e\r\n\u003c/section\u003e\r\n\u003csection class=\"business-talking\" id=\"pricing\"\u003e\r\n\t\u003cdiv class=\"container\"\u003e\r\n        \u003ch2\u003eAccount solutions\u003c/h2\u003e\r\n    \u003c/div\u003e\r\n\t\t\t\u003csection class=\"row breath\"\u003e\r\n\r\n\t\t\t\u003ca href=\"/?signup=true\"\u003e\r\n\t\t\t\t\u003cdiv class=\"col-xs-4\"\u003e\r\n\t\t\t\t\t\u003cdiv class=\"pricing color1\"\u003e\r\n\t\t\t\t\t\t\u003cdiv class=\"planname\"\u003eRegular\u003c/div\u003e\r\n\t\t\t\t\t\t\u003cdiv class=\"price\"\u003eFREE\u003c/div\u003e\r\n\t\t\t\t\t\t\u003cdiv class=\"billing\"\u003e100 messages \u003cspan class=\"per\"\u003e/Year\u003c/span\u003e\u003c/div\u003e\r\n                        \u003cdiv class=\"billing\"\u003e10 contacts\u003c/div\u003e\r\n\t\t\t\t\t\u003c/div\u003e\r\n\t\t\t\t\u003c/div\u003e\r\n\t\t\t\u003c/a\u003e\r\n\t\t\t\t\r\n\t\t\t\u003ca href=\"/upgrade/?A=premium\"\u003e\r\n                \u003cdiv class=\"col-xs-4\"\u003e\r\n\t\t\t\t\t\u003cdiv class=\"pricing color2\"\u003e\r\n\t\t\t\t\t\t\u003cdiv class=\"planname\"\u003ePremium\u003c/div\u003e\r\n\t\t\t\t\t\t\u003cdiv class=\"price\"\u003e \u003cspan class=\"curr\"\u003e$\u003c/span\u003e29\u003c/div\u003e\r\n\t\t\t\t\t\t\u003cdiv class=\"billing\"\u003e1000 messages \u003cspan class=\"per\"\u003e/Year\u003c/span\u003e\u003c/div\u003e\r\n                        \u003cdiv class=\"billing\"\u003e20 contacts\u003c/div\u003e\r\n\t\t\t\t\t\u003c/div\u003e\r\n\t\t\t\t\u003c/div\u003e\r\n\t\t\t\u003c/a\u003e\r\n\t\t\t\r\n            \u003ca href=\"/upgrade/?A=business\"\u003e\r\n\t\t\t\t\u003cdiv class=\"col-xs-4\"\u003e\r\n\t\t\t\t\t\u003cdiv class=\"pricing color3\"\u003e\r\n\t\t\t\t\t\t\u003cdiv class=\"planname\"\u003eBusiness\u003c/div\u003e\r\n\t\t\t\t\t\t\u003cdiv class=\"price\"\u003e \u003cspan class=\"curr\"\u003e$\u003c/span\u003e89\u003c/div\u003e\r\n\t\t\t\t\t\t\u003cdiv class=\"billing\"\u003eNo limits\u003c/div\u003e\r\n                        \u003cdiv class=\"billing\"\u003eOther advantages\u003c/div\u003e\r\n\t\t\t\t\t\u003c/div\u003e\r\n\t\t\t\t\u003c/div\u003e\r\n\t\t\t\u003c/a\u003e\r\n\r\n\t\t\t\u003c/section\u003e\r\n\u003c/section\u003e\r\n\u003cdiv class=\"container\"\u003e\r\n\u003csection class=\"main-section contact\" id=\"contact\"\u003e\r\n\t\u003ch2\u003eContact or report a bug\u003c/h2\u003e\u003cbr\u003e\u003cbr\u003e\u003cbr\u003e\r\n            \u003cdiv class=\"w500px\"\u003e\r\n                 \u003cform method=\"post\" action=\"?#contact\"\u003e\r\n                    \u003cinput name=\"contact-id\" type=\"text\" class=\"input-text\" placeholder=\"Your ID (optional)\"\u003e\r\n                \t\u003ctextarea name=\"contact-txt\" cols=\"0\" rows=\"0\" required class=\"input-text text-area\" placeholder=\"Message *\"\u003e\u003c/textarea\u003e\r\n                    \u003cinput name=\"contact-me\" class=\"input-btn\" type=\"submit\" value=\"send message\"\u003e\r\n                  \u003c/form\u003e\r\n        \u003c/div\u003e\r\n\u003c/section\u003e\r\n\u003c/div\u003e\r\n\u003cscript type=\"text/javascript\"\u003e\r\nfunction CopyThis(id)\r\n{\r\n    document.getElementById(id).focus();\r\n    document.getElementById(id).select();\r\n\tdocument.execCommand('copy');\r\n}\r\n\u003c/script\u003e\r\n\u003csection class=\"footer\"\u003e\u003c/section\u003e\r\n\u003c/body\u003e\r\n\u003c/html\u003e\r\n","pageTitle":"Appaloosa Chat","responseHeaders":{"CACHE-CONTROL":"no-store, no-cache, must-revalidate","CONTENT-TYPE":"text/html; charset=UTF-8","DATE":"Mon, 25 Jul 2016 16:11:47 GMT","EXPIRES":"Thu, 19 Nov 1981 08:52:00 GMT","PRAGMA":"no-cache","SERVER":"Apache","SET-COOKIE":"PHPSESSID=18vp400tqp1bvq47ridb1h9302; path=/"},"bitcoinAddresses":null,"sshKey":"","ftpFingerprint":"","ftpBanner":"","smtpFingerprint":"","smtpBanner":""}
